{
  "status": 1,
  "server_time": 1600613562447,
  "order_field": "selling_time",
  "order_headers": [
    {
      "field": "selling_time",
      "direction": [
        "DESC"
      ],
      "name": "最新"
    },
    {
      "field": "recommd",
      "direction": [],
      "name": "人气"
    },
    {
      "field": "price",
      "direction": [
        "DESC",
        "ASC"
      ],
      "name": "价格"
    }
  ],
  "order_direction": "DESC",
  "paging": {
    "is_last_page": false
  },
  "result": [
    {
      "storage_type": 4,
      "tag": "latest",
      "collect_num": 7,
      "pass_fair_show": 1,
      "server_name": "兰之雅",
      "level_desc": "60级",
      "highlights": [
        "月见黑"
      ],
      "kindid": 1,
      "equip_level": 60,
      "tag_key": "{\"sort_key\": \"recommd\", \"tag\": \"latest\", \"sort_order\": \"\"}",
      "area_name": "中国区-iOS",
      "desc_sumup_short": "SSR 55   六星式神 43   签到920天",
      "equip_type": "0",
      "price": 97900,
      "other_info": {
        "top_heros": [
          {
            "star": 6,
            "name": "烬天玉藻前",
            "level": 40,
            "max_level": true,
            "rarity": 5,
            "awake": 1,
            "heroId": 339,
            "icon": "https://cbg-yys.res.netease.com//game_res/hero/339/339.png"
          },
          {
            "star": 6,
            "name": "烬天玉藻前",
            "level": 40,
            "max_level": true,
            "rarity": 5,
            "awake": 1,
            "heroId": 339,
            "icon": "https://cbg-yys.res.netease.com//game_res/hero/339/339.png"
          },
          {
            "star": 6,
            "name": "御怨般若",
            "level": 40,
            "max_level": true,
            "rarity": 5,
            "awake": 1,
            "heroId": 331,
            "icon": "https://cbg-yys.res.netease.com//game_res/hero/331/331.png"
          },
          {
            "star": 6,
            "name": "稻荷神御馔津",
            "level": 40,
            "max_level": true,
            "rarity": 5,
            "awake": 1,
            "heroId": 326,
            "icon": "https://cbg-yys.res.netease.com//game_res/hero/326/326.png"
          },
          {
            "star": 6,
            "name": "少羽大天狗",
            "level": 40,
            "max_level": true,
            "rarity": 5,
            "awake": 1,
            "heroId": 315,
            "icon": "https://cbg-yys.res.netease.com//game_res/hero/315/315.png"
          }
        ],
        "level_desc": "60级",
        "highlights": [
          "月见黑"
        ],
        "desc_sumup": "SSR 55   六星式神 43   签到920天",
        "basic_attrs": [
          "SSR 55",
          "六星式神 43",
          "签到920天"
        ],
        "icon": "https://cbg-yys.res.netease.com//game_res/hero/339/339.png",
        "desc_sumup_short": "SSR 55   六星式神 43   签到920天"
      },
      "allow_urs_bargain": false,
      "expire_remain_seconds": 1179781,
      "serverid": 11,
      "icon": "https://cbg-yys.res.netease.com//game_res/hero/339/339.png",
      "game_ordersn": "202006262201616-11-YGMCYVBYPUN68",
      "platform_type": 1,
      "allow_bargain": false,
      "format_equip_name": "冲淡一切king",
      "game_channel": "netease"
    },
    {
      "storage_type": 4,
      "tag": "latest",
      "collect_num": 54,
      "pass_fair_show": 1,
      "server_name": "网易-相伴相随",
      "level_desc": "60级",
      "highlights": [
        "日月同辉",
        "鲤跃金松",
        "雪月华庭",
        "暖春翠庭"
      ],
      "kindid": 1,
      "equip_level": 60,
      "tag_key": "{\"sort_key\": \"recommd\", \"tag\": \"latest\", \"sort_order\": \"\"}",
      "area_name": "网易-双平台",
      "desc_sumup_short": "SSR 59   六星式神 89   签到1150天",
      "equip_type": "0",
      "price": 202000,
      "other_info": {
        "top_heros": [
          {
            "star": 6,
            "name": "稻荷神御馔津",
            "level": 40,
            "max_level": true,
            "rarity": 5,
            "awake": 1,
            "heroId": 326,
            "icon": "https://cbg-yys.res.netease.com//game_res/hero/326/326.png"
          },
          {
            "star": 6,
            "name": "烬天玉藻前",
            "level": 40,
            "max_level": true,
            "rarity": 5,
            "awake": 1,
            "heroId": 339,
            "icon": "https://cbg-yys.res.netease.com//game_res/hero/339/339.png"
          },
          {
            "star": 6,
            "name": "炼狱茨木童子",
            "level": 40,
            "max_level": true,
            "rarity": 5,
            "awake": 1,
            "heroId": 322,
            "icon": "https://cbg-yys.res.netease.com//game_res/hero/322/322.png"
          },
          {
            "star": 6,
            "name": "赤影妖刀姬",
            "level": 40,
            "max_level": true,
            "rarity": 5,
            "awake": 1,
            "heroId": 328,
            "icon": "https://cbg-yys.res.netease.com//game_res/hero/328/328.png"
          },
          {
            "star": 6,
            "name": "御怨般若",
            "level": 40,
            "max_level": true,
            "rarity": 5,
            "awake": 1,
            "heroId": 331,
            "icon": "https://cbg-yys.res.netease.com//game_res/hero/331/331.png"
          }
        ],
        "level_desc": "60级",
        "highlights": [
          "日月同辉",
          "鲤跃金松",
          "雪月华庭",
          "暖春翠庭"
        ],
        "desc_sumup": "SSR 59   六星式神 89   签到1150天",
        "basic_attrs": [
          "SSR 59",
          "六星式神 89",
          "签到1150天"
        ],
        "icon": "https://cbg-yys.res.netease.com//game_res/hero/326/326.png",
        "desc_sumup_short": "SSR 59   六星式神 89   签到1150天"
      },
      "allow_urs_bargain": false,
      "expire_remain_seconds": 1179755,
      "serverid": 12,
      "icon": "https://cbg-yys.res.netease.com//game_res/hero/326/326.png",
      "game_ordersn": "202007061801616-12-AOIECKSCNPIMP",
      "platform_type": 2,
      "allow_bargain": false,
      "format_equip_name": "よげんし",
      "game_channel": "netease"
    },
    {
      "storage_type": 4,
      "tag": "latest",
      "collect_num": 0,
      "pass_fair_show": 0,
      "server_name": "网易-两情相悦",
      "level_desc": "60级",
      "highlights": [],
      "kindid": 1,
      "equip_level": 60,
      "tag_key": "{\"sort_key\": \"recommd\", \"tag\": \"latest\", \"sort_order\": \"\"}",
      "area_name": "网易-双平台",
      "desc_sumup_short": "SSR 34   六星式神 18   签到595天",
      "equip_type": "0",
      "price": 60000,
      "other_info": {
        "top_heros": [
          {
            "star": 6,
            "name": "赤影妖刀姬",
            "level": 40,
            "max_level": true,
            "rarity": 5,
            "awake": 1,
            "heroId": 328,
            "icon": "https://cbg-yys.res.netease.com//game_res/hero/328/328.png"
          },
          {
            "star": 6,
            "name": "玉藻前",
            "level": 40,
            "max_level": true,
            "rarity": 4,
            "awake": 1,
            "heroId": 300,
            "icon": "https://cbg-yys.res.netease.com//game_res/hero/300/300.png"
          },
          {
            "star": 6,
            "name": "八岐大蛇",
            "level": 40,
            "max_level": true,
            "rarity": 4,
            "awake": 1,
            "heroId": 325,
            "icon": "https://cbg-yys.res.netease.com//game_res/hero/325/325.png"
          },
          {
            "star": 6,
            "name": "白藏主",
            "level": 40,
            "max_level": true,
            "rarity": 4,
            "awake": 1,
            "heroId": 316,
            "icon": "https://cbg-yys.res.netease.com//game_res/hero/316/316.png"
          },
          {
            "star": 6,
            "name": "八岐大蛇",
            "level": 40,
            "max_level": true,
            "rarity": 4,
            "awake": 1,
            "heroId": 325,
            "icon": "https://cbg-yys.res.netease.com//game_res/hero/325/325.png"
          }
        ],
        "level_desc": "60级",
        "highlights": [],
        "desc_sumup": "SSR 34   六星式神 18   签到595天",
        "basic_attrs": [
          "SSR 34",
          "六星式神 18",
          "签到595天"
        ],
        "icon": "https://cbg-yys.res.netease.com//game_res/hero/328/328.png",
        "desc_sumup_short": "SSR 34   六星式神 18   签到595天"
      },
      "allow_urs_bargain": false,
      "expire_remain_seconds": 1266115,
      "serverid": 3,
      "icon": "https://cbg-yys.res.netease.com//game_res/hero/328/328.png",
      "game_ordersn": "202009131401616-3-SDIMN8GU7DX10G",
      "platform_type": 2,
      "allow_bargain": false,
      "format_equip_name": "火火火哟",
      "game_channel": "netease"
    },
    {
      "storage_type": 4,
      "tag": "latest",
      "collect_num": 2,
      "pass_fair_show": 0,
      "server_name": "鬼灯的冷彻",
      "level_desc": "60级",
      "highlights": [
        "月见黑",
        "终极之巅"
      ],
      "kindid": 1,
      "equip_level": 60,
      "tag_key": "{\"sort_key\": \"recommd\", \"tag\": \"latest\", \"sort_order\": \"\"}",
      "area_name": "全平台互通新区",
      "desc_sumup_short": "SSR 29   六星式神 47   签到745天",
      "equip_type": "0",
      "price": 71000,
      "other_info": {
        "top_heros": [
          {
            "star": 6,
            "name": "聆海金鱼姬",
            "level": 40,
            "max_level": true,
            "rarity": 5,
            "awake": 1,
            "heroId": 346,
            "icon": "https://cbg-yys.res.netease.com//game_res/hero/346/346.png"
          },
          {
            "star": 6,
            "name": "御怨般若",
            "level": 40,
            "max_level": true,
            "rarity": 5,
            "awake": 1,
            "heroId": 331,
            "icon": "https://cbg-yys.res.netease.com//game_res/hero/331/331.png"
          },
          {
            "star": 6,
            "name": "烬天玉藻前",
            "level": 40,
            "max_level": true,
            "rarity": 5,
            "awake": 1,
            "heroId": 339,
            "icon": "https://cbg-yys.res.netease.com//game_res/hero/339/339.png"
          },
          {
            "star": 6,
            "name": "稻荷神御馔津",
            "level": 40,
            "max_level": true,
            "rarity": 5,
            "awake": 1,
            "heroId": 326,
            "icon": "https://cbg-yys.res.netease.com//game_res/hero/326/326.png"
          },
          {
            "star": 6,
            "name": "鬼王酒吞童子",
            "level": 40,
            "max_level": true,
            "rarity": 5,
            "awake": 1,
            "heroId": 341,
            "icon": "https://cbg-yys.res.netease.com//game_res/hero/341/341.png"
          }
        ],
        "level_desc": "60级",
        "highlights": [
          "月见黑",
          "终极之巅"
        ],
        "desc_sumup": "SSR 29   六星式神 47   签到745天",
        "basic_attrs": [
          "SSR 29",
          "六星式神 47",
          "签到745天"
        ],
        "icon": "https://cbg-yys.res.netease.com//game_res/hero/346/346.png",
        "desc_sumup_short": "SSR 29   六星式神 47   签到745天"
      },
      "allow_urs_bargain": true,
      "expire_remain_seconds": 1266112,
      "serverid": 27,
      "icon": "https://cbg-yys.res.netease.com//game_res/hero/346/346.png",
      "game_ordersn": "202009131401616-27-NKL9WEJDEHJA9",
      "platform_type": 2,
      "allow_bargain": true,
      "format_equip_name": "深海洋平",
      "game_channel": "netease"
    },
    {
      "storage_type": 4,
      "tag": "latest",
      "collect_num": 73,
      "pass_fair_show": 1,
      "server_name": "松之苍",
      "level_desc": "60级",
      "highlights": [
        "斗技3363",
        "征服世界",
        "地域·天下一",
        "终极之巅",
        "雪月华庭",
        "黑晴明"
      ],
      "kindid": 1,
      "equip_level": 60,
      "tag_key": "{\"sort_key\": \"recommd\", \"tag\": \"latest\", \"sort_order\": \"\"}",
      "area_name": "中国区-iOS",
      "desc_sumup_short": "SSR 99   六星式神 119   签到1297天",
      "equip_type": "0",
      "price": 2355500,
      "other_info": {
        "top_heros": [
          {
            "star": 6,
            "name": "炼狱茨木童子",
            "level": 40,
            "max_level": true,
            "rarity": 5,
            "awake": 1,
            "heroId": 322,
            "icon": "https://cbg-yys.res.netease.com//game_res/hero/322/322.png"
          },
          {
            "star": 6,
            "name": "御怨般若",
            "level": 40,
            "max_level": true,
            "rarity": 5,
            "awake": 1,
            "heroId": 331,
            "icon": "https://cbg-yys.res.netease.com//game_res/hero/331/331.png"
          },
          {
            "star": 6,
            "name": "鬼王酒吞童子",
            "level": 40,
            "max_level": true,
            "rarity": 5,
            "awake": 1,
            "heroId": 341,
            "icon": "https://cbg-yys.res.netease.com//game_res/hero/341/341.png"
          },
          {
            "star": 6,
            "name": "骁浪荒川之主",
            "level": 40,
            "max_level": true,
            "rarity": 5,
            "awake": 1,
            "heroId": 334,
            "icon": "https://cbg-yys.res.netease.com//game_res/hero/334/334.png"
          },
          {
            "star": 6,
            "name": "烬天玉藻前",
            "level": 40,
            "max_level": true,
            "rarity": 5,
            "awake": 1,
            "heroId": 339,
            "icon": "https://cbg-yys.res.netease.com//game_res/hero/339/339.png"
          }
        ],
        "level_desc": "60级",
        "highlights": [
          "斗技3363",
          "征服世界",
          "地域·天下一",
          "终极之巅",
          "雪月华庭",
          "黑晴明"
        ],
        "desc_sumup": "SSR 99   六星式神 119   签到1297天",
        "basic_attrs": [
          "SSR 99",
          "六星式神 119",
          "签到1297天"
        ],
        "icon": "https://cbg-yys.res.netease.com//game_res/hero/322/322.png",
        "desc_sumup_short": "SSR 99   六星式神 119   签到1297天"
      },
      "allow_urs_bargain": true,
      "expire_remain_seconds": 1179706,
      "serverid": 9,
      "icon": "https://cbg-yys.res.netease.com//game_res/hero/322/322.png",
      "game_ordersn": "202009031001616-9-MOHSVZS1AVMJVL",
      "platform_type": 1,
      "allow_bargain": true,
      "format_equip_name": "假1罚10",
      "game_channel": "netease"
    },
    {
      "storage_type": 4,
      "tag": "latest",
      "collect_num": 2,
      "pass_fair_show": 1,
      "server_name": "网易-携手同心",
      "level_desc": "60级",
      "highlights": [],
      "kindid": 1,
      "equip_level": 60,
      "tag_key": "{\"sort_key\": \"recommd\", \"tag\": \"latest\", \"sort_order\": \"\"}",
      "area_name": "网易-双平台",
      "desc_sumup_short": "SSR 51   六星式神 46   签到1139天",
      "equip_type": "0",
      "price": 75000,
      "other_info": {
        "top_heros": [
          {
            "star": 6,
            "name": "鬼王酒吞童子",
            "level": 40,
            "max_level": true,
            "rarity": 5,
            "awake": 1,
            "heroId": 341,
            "icon": "https://cbg-yys.res.netease.com//game_res/hero/341/341.png"
          },
          {
            "star": 6,
            "name": "聆海金鱼姬",
            "level": 40,
            "max_level": true,
            "rarity": 5,
            "awake": 1,
            "heroId": 346,
            "icon": "https://cbg-yys.res.netease.com//game_res/hero/346/346.png"
          },
          {
            "star": 6,
            "name": "炼狱茨木童子",
            "level": 40,
            "max_level": true,
            "rarity": 5,
            "awake": 1,
            "heroId": 322,
            "icon": "https://cbg-yys.res.netease.com//game_res/hero/322/322.png"
          },
          {
            "star": 6,
            "name": "稻荷神御馔津",
            "level": 40,
            "max_level": true,
            "rarity": 5,
            "awake": 1,
            "heroId": 326,
            "icon": "https://cbg-yys.res.netease.com//game_res/hero/326/326.png"
          },
          {
            "star": 6,
            "name": "鬼切",
            "level": 40,
            "max_level": true,
            "rarity": 4,
            "awake": 1,
            "heroId": 312,
            "icon": "https://cbg-yys.res.netease.com//game_res/hero/312/312.png"
          }
        ],
        "level_desc": "60级",
        "highlights": [],
        "desc_sumup": "SSR 51   六星式神 46   签到1139天",
        "basic_attrs": [
          "SSR 51",
          "六星式神 46",
          "签到1139天"
        ],
        "icon": "https://cbg-yys.res.netease.com//game_res/hero/341/341.png",
        "desc_sumup_short": "SSR 51   六星式神 46   签到1139天"
      },
      "allow_urs_bargain": true,
      "expire_remain_seconds": 1179697,
      "serverid": 17,
      "icon": "https://cbg-yys.res.netease.com//game_res/hero/341/341.png",
      "game_ordersn": "202009020901616-17-L4XXJZ7SOLMDS",
      "platform_type": 2,
      "allow_bargain": true,
      "format_equip_name": "Coco上岸咯",
      "game_channel": "netease"
    },
    {
      "storage_type": 4,
      "tag": "latest",
      "collect_num": 1,
      "pass_fair_show": 0,
      "server_name": "瀞灵廷",
      "level_desc": "60级",
      "highlights": [],
      "kindid": 1,
      "equip_level": 60,
      "tag_key": "{\"sort_key\": \"recommd\", \"tag\": \"latest\", \"sort_order\": \"\"}",
      "area_name": "全平台互通新区",
      "desc_sumup_short": "SSR 11   六星式神 12   签到262天",
      "equip_type": "0",
      "price": 29900,
      "other_info": {
        "top_heros": [
          {
            "star": 6,
            "name": "烬天玉藻前",
            "level": 40,
            "max_level": true,
            "rarity": 5,
            "awake": 1,
            "heroId": 339,
            "icon": "https://cbg-yys.res.netease.com//game_res/hero/339/339.png"
          },
          {
            "star": 6,
            "name": "烬天玉藻前",
            "level": 40,
            "max_level": true,
            "rarity": 5,
            "awake": 1,
            "heroId": 339,
            "icon": "https://cbg-yys.res.netease.com//game_res/hero/339/339.png"
          },
          {
            "star": 6,
            "name": "聆海金鱼姬",
            "level": 40,
            "max_level": true,
            "rarity": 5,
            "awake": 1,
            "heroId": 346,
            "icon": "https://cbg-yys.res.netease.com//game_res/hero/346/346.png"
          },
          {
            "star": 6,
            "name": "鬼王酒吞童子",
            "level": 40,
            "max_level": true,
            "rarity": 5,
            "awake": 1,
            "heroId": 341,
            "icon": "https://cbg-yys.res.netease.com//game_res/hero/341/341.png"
          },
          {
            "star": 6,
            "name": "泷夜叉姬",
            "level": 40,
            "max_level": true,
            "rarity": 4,
            "awake": 1,
            "heroId": 338,
            "icon": "https://cbg-yys.res.netease.com//game_res/hero/338/338.png"
          }
        ],
        "level_desc": "60级",
        "highlights": [],
        "desc_sumup": "SSR 11   六星式神 12   签到262天",
        "basic_attrs": [
          "SSR 11",
          "六星式神 12",
          "签到262天"
        ],
        "icon": "https://cbg-yys.res.netease.com//game_res/hero/339/339.png",
        "desc_sumup_short": "SSR 11   六星式神 12   签到262天"
      },
      "allow_urs_bargain": false,
      "expire_remain_seconds": 1266066,
      "serverid": 41,
      "icon": "https://cbg-yys.res.netease.com//game_res/hero/339/339.png",
      "game_ordersn": "202009131401616-41-F9JN5PFQBQDVA",
      "platform_type": 1,
      "allow_bargain": false,
      "format_equip_name": "李知恩",
      "game_channel": "netease"
    },
    {
      "storage_type": 4,
      "tag": "latest",
      "collect_num": 18,
      "pass_fair_show": 1,
      "server_name": "深情厚谊",
      "level_desc": "60级",
      "highlights": [],
      "kindid": 1,
      "equip_level": 60,
      "tag_key": "{\"sort_key\": \"recommd\", \"tag\": \"latest\", \"sort_order\": \"\"}",
      "area_name": "全平台互通新区",
      "desc_sumup_short": "SSR 11   六星式神 3   签到640天",
      "equip_type": "0",
      "price": 55500,
      "other_info": {
        "top_heros": [
          {
            "star": 6,
            "name": "雪童子",
            "level": 40,
            "max_level": true,
            "rarity": 4,
            "awake": 1,
            "heroId": 292,
            "icon": "https://cbg-yys.res.netease.com//game_res/hero/292/292.png"
          },
          {
            "star": 6,
            "name": "八岐大蛇",
            "level": 40,
            "max_level": true,
            "rarity": 4,
            "awake": 1,
            "heroId": 325,
            "icon": "https://cbg-yys.res.netease.com//game_res/hero/325/325.png"
          },
          {
            "star": 6,
            "name": "以津真天",
            "level": 40,
            "max_level": true,
            "rarity": 3,
            "awake": 1,
            "heroId": 286,
            "icon": "https://cbg-yys.res.netease.com//game_res/hero/286/286.png"
          },
          {
            "star": 2,
            "name": "阎魔",
            "level": 20,
            "max_level": false,
            "rarity": 4,
            "awake": 1,
            "heroId": 255,
            "icon": "https://cbg-yys.res.netease.com//game_res/hero/255/255.png"
          },
          {
            "star": 2,
            "name": "白藏主",
            "level": 20,
            "max_level": false,
            "rarity": 4,
            "awake": 1,
            "heroId": 316,
            "icon": "https://cbg-yys.res.netease.com//game_res/hero/316/316.png"
          }
        ],
        "level_desc": "60级",
        "highlights": [],
        "desc_sumup": "SSR 11   六星式神 3   签到640天",
        "basic_attrs": [
          "SSR 11",
          "六星式神 3",
          "签到640天"
        ],
        "icon": "https://cbg-yys.res.netease.com//game_res/hero/292/292.png",
        "desc_sumup_short": "SSR 11   六星式神 3   签到640天"
      },
      "allow_urs_bargain": false,
      "expire_remain_seconds": 1179662,
      "serverid": 4,
      "icon": "https://cbg-yys.res.netease.com//game_res/hero/292/292.png",
      "game_ordersn": "202008281501616-4-K9B12QPQUDQ4KS",
      "platform_type": 2,
      "allow_bargain": false,
      "format_equip_name": "超多蓝票舅妈蛇",
      "game_channel": "netease"
    },
    {
      "storage_type": 4,
      "tag": "latest",
      "collect_num": 1,
      "pass_fair_show": 0,
      "server_name": "网易-相伴相随",
      "level_desc": "60级",
      "highlights": [
        "日月同辉"
      ],
      "kindid": 1,
      "equip_level": 60,
      "tag_key": "{\"sort_key\": \"recommd\", \"tag\": \"latest\", \"sort_order\": \"\"}",
      "area_name": "网易-双平台",
      "desc_sumup_short": "SSR 39   六星式神 36   签到560天",
      "equip_type": "0",
      "price": 45000,
      "other_info": {
        "top_heros": [
          {
            "star": 6,
            "name": "炼狱茨木童子",
            "level": 40,
            "max_level": true,
            "rarity": 5,
            "awake": 1,
            "heroId": 322,
            "icon": "https://cbg-yys.res.netease.com//game_res/hero/322/322.png"
          },
          {
            "star": 6,
            "name": "赤影妖刀姬",
            "level": 40,
            "max_level": true,
            "rarity": 5,
            "awake": 1,
            "heroId": 328,
            "icon": "https://cbg-yys.res.netease.com//game_res/hero/328/328.png"
          },
          {
            "star": 6,
            "name": "少羽大天狗",
            "level": 40,
            "max_level": true,
            "rarity": 5,
            "awake": 1,
            "heroId": 315,
            "icon": "https://cbg-yys.res.netease.com//game_res/hero/315/315.png"
          },
          {
            "star": 6,
            "name": "鬼王酒吞童子",
            "level": 40,
            "max_level": true,
            "rarity": 5,
            "awake": 1,
            "heroId": 341,
            "icon": "https://cbg-yys.res.netease.com//game_res/hero/341/341.png"
          },
          {
            "star": 6,
            "name": "少羽大天狗",
            "level": 40,
            "max_level": true,
            "rarity": 5,
            "awake": 1,
            "heroId": 315,
            "icon": "https://cbg-yys.res.netease.com//game_res/hero/315/315.png"
          }
        ],
        "level_desc": "60级",
        "highlights": [
          "日月同辉"
        ],
        "desc_sumup": "SSR 39   六星式神 36   签到560天",
        "basic_attrs": [
          "SSR 39",
          "六星式神 36",
          "签到560天"
        ],
        "icon": "https://cbg-yys.res.netease.com//game_res/hero/322/322.png",
        "desc_sumup_short": "SSR 39   六星式神 36   签到560天"
      },
      "allow_urs_bargain": true,
      "expire_remain_seconds": 1266024,
      "serverid": 12,
      "icon": "https://cbg-yys.res.netease.com//game_res/hero/322/322.png",
      "game_ordersn": "202009131401616-12-5TR64GFBEKXIV",
      "platform_type": 2,
      "allow_bargain": true,
      "format_equip_name": "江映千雪",
      "game_channel": "netease"
    },
    {
      "storage_type": 4,
      "tag": "latest",
      "collect_num": 0,
      "pass_fair_show": 0,
      "server_name": "兰之雅",
      "level_desc": "60级",
      "highlights": [
        "月见黑",
        "赤之流火"
      ],
      "kindid": 1,
      "equip_level": 60,
      "tag_key": "{\"sort_key\": \"recommd\", \"tag\": \"latest\", \"sort_order\": \"\"}",
      "area_name": "中国区-iOS",
      "desc_sumup_short": "SSR 21   六星式神 34   签到676天",
      "equip_type": "0",
      "price": 50000,
      "other_info": {
        "top_heros": [
          {
            "star": 6,
            "name": "烬天玉藻前",
            "level": 40,
            "max_level": true,
            "rarity": 5,
            "awake": 1,
            "heroId": 339,
            "icon": "https://cbg-yys.res.netease.com//game_res/hero/339/339.png"
          },
          {
            "star": 6,
            "name": "炼狱茨木童子",
            "level": 40,
            "max_level": true,
            "rarity": 5,
            "awake": 1,
            "heroId": 322,
            "icon": "https://cbg-yys.res.netease.com//game_res/hero/322/322.png"
          },
          {
            "star": 6,
            "name": "聆海金鱼姬",
            "level": 40,
            "max_level": true,
            "rarity": 5,
            "awake": 1,
            "heroId": 346,
            "icon": "https://cbg-yys.res.netease.com//game_res/hero/346/346.png"
          },
          {
            "star": 6,
            "name": "面灵气",
            "level": 40,
            "max_level": true,
            "rarity": 4,
            "awake": 1,
            "heroId": 311,
            "icon": "https://cbg-yys.res.netease.com//game_res/hero/311/311.png"
          },
          {
            "star": 6,
            "name": "不知火",
            "level": 40,
            "max_level": true,
            "rarity": 4,
            "awake": 1,
            "heroId": 330,
            "icon": "https://cbg-yys.res.netease.com//game_res/hero/330/330.png"
          }
        ],
        "level_desc": "60级",
        "highlights": [
          "月见黑",
          "赤之流火"
        ],
        "desc_sumup": "SSR 21   六星式神 34   签到676天",
        "basic_attrs": [
          "SSR 21",
          "六星式神 34",
          "签到676天"
        ],
        "icon": "https://cbg-yys.res.netease.com//game_res/hero/339/339.png",
        "desc_sumup_short": "SSR 21   六星式神 34   签到676天"
      },
      "allow_urs_bargain": false,
      "expire_remain_seconds": 1265997,
      "serverid": 11,
      "icon": "https://cbg-yys.res.netease.com//game_res/hero/339/339.png",
      "game_ordersn": "202009131401616-11-EKEMEKSZBMD4X",
      "platform_type": 1,
      "allow_bargain": false,
      "format_equip_name": "清清大佬在此",
      "game_channel": "netease"
    },
    {
      "storage_type": 4,
      "tag": "latest",
      "collect_num": 1,
      "pass_fair_show": 1,
      "server_name": "兰之雅",
      "level_desc": "60级",
      "highlights": [
        "赤之流火"
      ],
      "kindid": 1,
      "equip_level": 60,
      "tag_key": "{\"sort_key\": \"recommd\", \"tag\": \"latest\", \"sort_order\": \"\"}",
      "area_name": "中国区-iOS",
      "desc_sumup_short": "SSR 35   六星式神 57   签到754天",
      "equip_type": "0",
      "price": 100000,
      "other_info": {
        "top_heros": [
          {
            "star": 6,
            "name": "赤影妖刀姬",
            "level": 40,
            "max_level": true,
            "rarity": 5,
            "awake": 1,
            "heroId": 328,
            "icon": "https://cbg-yys.res.netease.com//game_res/hero/328/328.png"
          },
          {
            "star": 6,
            "name": "稻荷神御馔津",
            "level": 40,
            "max_level": true,
            "rarity": 5,
            "awake": 1,
            "heroId": 326,
            "icon": "https://cbg-yys.res.netease.com//game_res/hero/326/326.png"
          },
          {
            "star": 6,
            "name": "御怨般若",
            "level": 40,
            "max_level": true,
            "rarity": 5,
            "awake": 1,
            "heroId": 331,
            "icon": "https://cbg-yys.res.netease.com//game_res/hero/331/331.png"
          },
          {
            "star": 6,
            "name": "鬼王酒吞童子",
            "level": 40,
            "max_level": true,
            "rarity": 5,
            "awake": 1,
            "heroId": 341,
            "icon": "https://cbg-yys.res.netease.com//game_res/hero/341/341.png"
          },
          {
            "star": 6,
            "name": "聆海金鱼姬",
            "level": 40,
            "max_level": true,
            "rarity": 5,
            "awake": 1,
            "heroId": 346,
            "icon": "https://cbg-yys.res.netease.com//game_res/hero/346/346.png"
          }
        ],
        "level_desc": "60级",
        "highlights": [
          "赤之流火"
        ],
        "desc_sumup": "SSR 35   六星式神 57   签到754天",
        "basic_attrs": [
          "SSR 35",
          "六星式神 57",
          "签到754天"
        ],
        "icon": "https://cbg-yys.res.netease.com//game_res/hero/328/328.png",
        "desc_sumup_short": "SSR 35   六星式神 57   签到754天"
      },
      "allow_urs_bargain": true,
      "expire_remain_seconds": 1179558,
      "serverid": 11,
      "icon": "https://cbg-yys.res.netease.com//game_res/hero/328/328.png",
      "game_ordersn": "202004092101616-11-FFTSVUUDCJZWN",
      "platform_type": 1,
      "allow_bargain": true,
      "format_equip_name": "水水狐不归",
      "game_channel": "netease"
    },
    {
      "storage_type": 4,
      "tag": "latest",
      "collect_num": 2,
      "pass_fair_show": 0,
      "server_name": "春之樱",
      "level_desc": "60级",
      "highlights": [
        "雪月华庭",
        "暖春翠庭"
      ],
      "kindid": 1,
      "equip_level": 60,
      "tag_key": "{\"sort_key\": \"recommd\", \"tag\": \"latest\", \"sort_order\": \"\"}",
      "area_name": "中国区-iOS",
      "desc_sumup_short": "SSR 43   六星式神 49   签到1074天",
      "equip_type": "0",
      "price": 120000,
      "other_info": {
        "top_heros": [
          {
            "star": 6,
            "name": "赤影妖刀姬",
            "level": 40,
            "max_level": true,
            "rarity": 5,
            "awake": 1,
            "heroId": 328,
            "icon": "https://cbg-yys.res.netease.com//game_res/hero/328/328.png"
          },
          {
            "star": 6,
            "name": "稻荷神御馔津",
            "level": 40,
            "max_level": true,
            "rarity": 5,
            "awake": 1,
            "heroId": 326,
            "icon": "https://cbg-yys.res.netease.com//game_res/hero/326/326.png"
          },
          {
            "star": 6,
            "name": "御怨般若",
            "level": 40,
            "max_level": true,
            "rarity": 5,
            "awake": 1,
            "heroId": 331,
            "icon": "https://cbg-yys.res.netease.com//game_res/hero/331/331.png"
          },
          {
            "star": 6,
            "name": "烬天玉藻前",
            "level": 40,
            "max_level": true,
            "rarity": 5,
            "awake": 1,
            "heroId": 339,
            "icon": "https://cbg-yys.res.netease.com//game_res/hero/339/339.png"
          },
          {
            "star": 6,
            "name": "少羽大天狗",
            "level": 40,
            "max_level": true,
            "rarity": 5,
            "awake": 1,
            "heroId": 315,
            "icon": "https://cbg-yys.res.netease.com//game_res/hero/315/315.png"
          }
        ],
        "level_desc": "60级",
        "highlights": [
          "雪月华庭",
          "暖春翠庭"
        ],
        "desc_sumup": "SSR 43   六星式神 49   签到1074天",
        "basic_attrs": [
          "SSR 43",
          "六星式神 49",
          "签到1074天"
        ],
        "icon": "https://cbg-yys.res.netease.com//game_res/hero/328/328.png",
        "desc_sumup_short": "SSR 43   六星式神 49   签到1074天"
      },
      "allow_urs_bargain": true,
      "expire_remain_seconds": 1265954,
      "serverid": 20,
      "icon": "https://cbg-yys.res.netease.com//game_res/hero/328/328.png",
      "game_ordersn": "202009131401616-20-XFGIV6VTOTL8R",
      "platform_type": 1,
      "allow_bargain": true,
      "format_equip_name": "我们好遗憾啊",
      "game_channel": "netease"
    },
    {
      "storage_type": 4,
      "tag": "latest",
      "collect_num": 0,
      "pass_fair_show": 0,
      "server_name": "初心未改",
      "level_desc": "60级",
      "highlights": [
        "地域·天下一",
        "终极之巅"
      ],
      "kindid": 1,
      "equip_level": 60,
      "tag_key": "{\"sort_key\": \"recommd\", \"tag\": \"latest\", \"sort_order\": \"\"}",
      "area_name": "全平台互通新区",
      "desc_sumup_short": "SSR 36   六星式神 50   签到705天",
      "equip_type": "0",
      "price": 110000,
      "other_info": {
        "top_heros": [
          {
            "star": 6,
            "name": "稻荷神御馔津",
            "level": 40,
            "max_level": true,
            "rarity": 5,
            "awake": 1,
            "heroId": 326,
            "icon": "https://cbg-yys.res.netease.com//game_res/hero/326/326.png"
          },
          {
            "star": 6,
            "name": "御怨般若",
            "level": 40,
            "max_level": true,
            "rarity": 5,
            "awake": 1,
            "heroId": 331,
            "icon": "https://cbg-yys.res.netease.com//game_res/hero/331/331.png"
          },
          {
            "star": 6,
            "name": "赤影妖刀姬",
            "level": 40,
            "max_level": true,
            "rarity": 5,
            "awake": 1,
            "heroId": 328,
            "icon": "https://cbg-yys.res.netease.com//game_res/hero/328/328.png"
          },
          {
            "star": 6,
            "name": "炼狱茨木童子",
            "level": 40,
            "max_level": true,
            "rarity": 5,
            "awake": 1,
            "heroId": 322,
            "icon": "https://cbg-yys.res.netease.com//game_res/hero/322/322.png"
          },
          {
            "star": 6,
            "name": "烬天玉藻前",
            "level": 40,
            "max_level": true,
            "rarity": 5,
            "awake": 1,
            "heroId": 339,
            "icon": "https://cbg-yys.res.netease.com//game_res/hero/339/339.png"
          }
        ],
        "level_desc": "60级",
        "highlights": [
          "地域·天下一",
          "终极之巅"
        ],
        "desc_sumup": "SSR 36   六星式神 50   签到705天",
        "basic_attrs": [
          "SSR 36",
          "六星式神 50",
          "签到705天"
        ],
        "icon": "https://cbg-yys.res.netease.com//game_res/hero/326/326.png",
        "desc_sumup_short": "SSR 36   六星式神 50   签到705天"
      },
      "allow_urs_bargain": false,
      "expire_remain_seconds": 1265924,
      "serverid": 28,
      "icon": "https://cbg-yys.res.netease.com//game_res/hero/326/326.png",
      "game_ordersn": "202009130601616-28-X2ZR4E2CJQKZP",
      "platform_type": 2,
      "allow_bargain": false,
      "format_equip_name": "वाक्वा白灵",
      "game_channel": "netease"
    },
    {
      "storage_type": 4,
      "tag": "latest",
      "collect_num": 2,
      "pass_fair_show": 0,
      "server_name": "全球国际区",
      "level_desc": "60级",
      "highlights": [
        "斗技2400",
        "月见黑",
        "地域·天下一",
        "终极之巅"
      ],
      "kindid": 1,
      "equip_level": 60,
      "tag_key": "{\"sort_key\": \"recommd\", \"tag\": \"latest\", \"sort_order\": \"\"}",
      "area_name": "全平台互通新区",
      "desc_sumup_short": "SSR 42   六星式神 54   签到655天",
      "equip_type": "0",
      "price": 290000,
      "other_info": {
        "top_heros": [
          {
            "star": 6,
            "name": "炼狱茨木童子",
            "level": 40,
            "max_level": true,
            "rarity": 5,
            "awake": 1,
            "heroId": 322,
            "icon": "https://cbg-yys.res.netease.com//game_res/hero/322/322.png"
          },
          {
            "star": 6,
            "name": "缚骨清姬",
            "level": 40,
            "max_level": true,
            "rarity": 5,
            "awake": 1,
            "heroId": 352,
            "icon": "https://cbg-yys.res.netease.com//game_res/hero/352/352.png"
          },
          {
            "star": 6,
            "name": "御怨般若",
            "level": 40,
            "max_level": true,
            "rarity": 5,
            "awake": 1,
            "heroId": 331,
            "icon": "https://cbg-yys.res.netease.com//game_res/hero/331/331.png"
          },
          {
            "star": 6,
            "name": "鬼王酒吞童子",
            "level": 40,
            "max_level": true,
            "rarity": 5,
            "awake": 1,
            "heroId": 341,
            "icon": "https://cbg-yys.res.netease.com//game_res/hero/341/341.png"
          },
          {
            "star": 6,
            "name": "烬天玉藻前",
            "level": 40,
            "max_level": true,
            "rarity": 5,
            "awake": 1,
            "heroId": 339,
            "icon": "https://cbg-yys.res.netease.com//game_res/hero/339/339.png"
          }
        ],
        "level_desc": "60级",
        "highlights": [
          "斗技2400",
          "月见黑",
          "地域·天下一",
          "终极之巅"
        ],
        "desc_sumup": "SSR 42   六星式神 54   签到655天",
        "basic_attrs": [
          "SSR 42",
          "六星式神 54",
          "签到655天"
        ],
        "icon": "https://cbg-yys.res.netease.com//game_res/hero/322/322.png",
        "desc_sumup_short": "SSR 42   六星式神 54   签到655天"
      },
      "allow_urs_bargain": false,
      "expire_remain_seconds": 1265922,
      "serverid": 33,
      "icon": "https://cbg-yys.res.netease.com//game_res/hero/322/322.png",
      "game_ordersn": "202009131401616-33-4EMXEYNPDOHMF",
      "platform_type": 2,
      "allow_bargain": false,
      "format_equip_name": "雨又萧萧",
      "game_channel": "netease"
    }
  ],
  "pager": {
    "cur_page": 94,
    "total_pages": 100
  }
}