{
  "status": 1,
  "server_time": 1600784240659,
  "order_field": "selling_time",
  "order_headers": [
    {
      "field": "selling_time",
      "direction": [
        "DESC"
      ],
      "name": "最新"
    },
    {
      "field": "recommd",
      "direction": [],
      "name": "人气"
    },
    {
      "field": "price",
      "direction": [
        "DESC",
        "ASC"
      ],
      "name": "价格"
    }
  ],
  "order_direction": "DESC",
  "paging": {
    "is_last_page": false
  },
  "result": [
    {
      "storage_type": 4,
      "tag": "latest",
      "collect_num": 0,
      "pass_fair_show": 0,
      "server_name": "游梦迷蝶",
      "level_desc": "49级",
      "highlights": [],
      "kindid": 1,
      "equip_level": 49,
      "tag_key": "{\"sort_key\": \"recommd\", \"tag\": \"latest\", \"sort_order\": \"\"}",
      "area_name": "全平台互通新区",
      "desc_sumup_short": "SSR 35   六星式神 16   签到379天",
      "equip_type": "0",
      "price": 52000,
      "other_info": {
        "top_heros": [
          {
            "star": 6,
            "name": "炼狱茨木童子",
            "level": 40,
            "max_level": true,
            "rarity": 5,
            "awake": 1,
            "heroId": 322,
            "icon": "https://cbg-yys.res.netease.com//game_res/hero/322/322.png"
          },
          {
            "star": 6,
            "name": "聆海金鱼姬",
            "level": 40,
            "max_level": true,
            "rarity": 5,
            "awake": 1,
            "heroId": 346,
            "icon": "https://cbg-yys.res.netease.com//game_res/hero/346/346.png"
          },
          {
            "star": 6,
            "name": "面灵气",
            "level": 40,
            "max_level": true,
            "rarity": 4,
            "awake": 1,
            "heroId": 311,
            "icon": "https://cbg-yys.res.netease.com//game_res/hero/311/311.png"
          },
          {
            "star": 6,
            "name": "玉藻前",
            "level": 40,
            "max_level": true,
            "rarity": 4,
            "awake": 1,
            "heroId": 300,
            "icon": "https://cbg-yys.res.netease.com//game_res/hero/300/300.png"
          },
          {
            "star": 6,
            "name": "辉夜姬",
            "level": 40,
            "max_level": true,
            "rarity": 4,
            "awake": 1,
            "heroId": 280,
            "icon": "https://cbg-yys.res.netease.com//game_res/hero/280/280.png"
          }
        ],
        "level_desc": "49级",
        "highlights": [],
        "desc_sumup": "SSR 35   六星式神 16   签到379天",
        "basic_attrs": [
          "SSR 35",
          "六星式神 16",
          "签到379天"
        ],
        "icon": "https://cbg-yys.res.netease.com//game_res/hero/322/322.png",
        "desc_sumup_short": "SSR 35   六星式神 16   签到379天"
      },
      "allow_urs_bargain": false,
      "expire_remain_seconds": 1289729,
      "serverid": 35,
      "icon": "https://cbg-yys.res.netease.com//game_res/hero/322/322.png",
      "game_ordersn": "202009152001616-35-1PHYD94KUSMRF",
      "platform_type": 2,
      "allow_bargain": false,
      "format_equip_name": "笼中的七星异人",
      "game_channel": "netease"
    },
    {
      "storage_type": 4,
      "tag": "latest",
      "collect_num": 77,
      "pass_fair_show": 1,
      "server_name": "网易-相伴相随",
      "level_desc": "60级",
      "highlights": [],
      "kindid": 1,
      "equip_level": 60,
      "tag_key": "{\"sort_key\": \"recommd\", \"tag\": \"latest\", \"sort_order\": \"\"}",
      "area_name": "网易-双平台",
      "desc_sumup_short": "SSR 31   六星式神 40   签到912天",
      "equip_type": "0",
      "price": 62000,
      "other_info": {
        "top_heros": [
          {
            "star": 6,
            "name": "骁浪荒川之主",
            "level": 40,
            "max_level": true,
            "rarity": 5,
            "awake": 1,
            "heroId": 334,
            "icon": "https://cbg-yys.res.netease.com//game_res/hero/334/334.png"
          },
          {
            "star": 6,
            "name": "天剑韧心鬼切",
            "level": 40,
            "max_level": true,
            "rarity": 5,
            "awake": 1,
            "heroId": 343,
            "icon": "https://cbg-yys.res.netease.com//game_res/hero/343/343.png"
          },
          {
            "star": 6,
            "name": "炼狱茨木童子",
            "level": 40,
            "max_level": true,
            "rarity": 5,
            "awake": 1,
            "heroId": 322,
            "icon": "https://cbg-yys.res.netease.com//game_res/hero/322/322.png"
          },
          {
            "star": 6,
            "name": "赤影妖刀姬",
            "level": 40,
            "max_level": true,
            "rarity": 5,
            "awake": 1,
            "heroId": 328,
            "icon": "https://cbg-yys.res.netease.com//game_res/hero/328/328.png"
          },
          {
            "star": 6,
            "name": "烬天玉藻前",
            "level": 40,
            "max_level": true,
            "rarity": 5,
            "awake": 1,
            "heroId": 339,
            "icon": "https://cbg-yys.res.netease.com//game_res/hero/339/339.png"
          }
        ],
        "level_desc": "60级",
        "highlights": [],
        "desc_sumup": "SSR 31   六星式神 40   签到912天",
        "basic_attrs": [
          "SSR 31",
          "六星式神 40",
          "签到912天"
        ],
        "icon": "https://cbg-yys.res.netease.com//game_res/hero/334/334.png",
        "desc_sumup_short": "SSR 31   六星式神 40   签到912天"
      },
      "allow_urs_bargain": false,
      "expire_remain_seconds": 1203318,
      "serverid": 12,
      "icon": "https://cbg-yys.res.netease.com//game_res/hero/334/334.png",
      "game_ordersn": "202009142001616-12-NHNMEI6Y4GPYN",
      "platform_type": 1,
      "allow_bargain": false,
      "format_equip_name": "金蛇皮多五星卡多",
      "game_channel": "netease"
    },
    {
      "storage_type": 4,
      "tag": "latest",
      "collect_num": 189,
      "pass_fair_show": 1,
      "server_name": "松之苍",
      "level_desc": "60级",
      "highlights": [
        "月见黑"
      ],
      "kindid": 1,
      "equip_level": 60,
      "tag_key": "{\"sort_key\": \"recommd\", \"tag\": \"latest\", \"sort_order\": \"\"}",
      "area_name": "中国区-iOS",
      "desc_sumup_short": "SSR 44   六星式神 70   签到1212天",
      "equip_type": "0",
      "price": 109900,
      "other_info": {
        "top_heros": [
          {
            "star": 6,
            "name": "稻荷神御馔津",
            "level": 40,
            "max_level": true,
            "rarity": 5,
            "awake": 1,
            "heroId": 326,
            "icon": "https://cbg-yys.res.netease.com//game_res/hero/326/326.png"
          },
          {
            "star": 6,
            "name": "御怨般若",
            "level": 40,
            "max_level": true,
            "rarity": 5,
            "awake": 1,
            "heroId": 331,
            "icon": "https://cbg-yys.res.netease.com//game_res/hero/331/331.png"
          },
          {
            "star": 6,
            "name": "少羽大天狗",
            "level": 40,
            "max_level": true,
            "rarity": 5,
            "awake": 1,
            "heroId": 315,
            "icon": "https://cbg-yys.res.netease.com//game_res/hero/315/315.png"
          },
          {
            "star": 6,
            "name": "聆海金鱼姬",
            "level": 40,
            "max_level": true,
            "rarity": 5,
            "awake": 1,
            "heroId": 346,
            "icon": "https://cbg-yys.res.netease.com//game_res/hero/346/346.png"
          },
          {
            "star": 6,
            "name": "烬天玉藻前",
            "level": 40,
            "max_level": true,
            "rarity": 5,
            "awake": 1,
            "heroId": 339,
            "icon": "https://cbg-yys.res.netease.com//game_res/hero/339/339.png"
          }
        ],
        "level_desc": "60级",
        "highlights": [
          "月见黑"
        ],
        "desc_sumup": "SSR 44   六星式神 70   签到1212天",
        "basic_attrs": [
          "SSR 44",
          "六星式神 70",
          "签到1212天"
        ],
        "icon": "https://cbg-yys.res.netease.com//game_res/hero/326/326.png",
        "desc_sumup_short": "SSR 44   六星式神 70   签到1212天"
      },
      "allow_urs_bargain": false,
      "expire_remain_seconds": 1203282,
      "serverid": 9,
      "icon": "https://cbg-yys.res.netease.com//game_res/hero/326/326.png",
      "game_ordersn": "202009101101616-9-XJG2LUFDNQ5O7D",
      "platform_type": 1,
      "allow_bargain": false,
      "format_equip_name": "双烬18魂土名士",
      "game_channel": "netease"
    },
    {
      "storage_type": 4,
      "tag": "latest",
      "collect_num": 4,
      "pass_fair_show": 1,
      "server_name": "松之苍",
      "level_desc": "60级",
      "highlights": [],
      "kindid": 1,
      "equip_level": 60,
      "tag_key": "{\"sort_key\": \"recommd\", \"tag\": \"latest\", \"sort_order\": \"\"}",
      "area_name": "中国区-iOS",
      "desc_sumup_short": "SSR 29   六星式神 38   签到757天",
      "equip_type": "0",
      "price": 70000,
      "other_info": {
        "top_heros": [
          {
            "star": 6,
            "name": "烬天玉藻前",
            "level": 40,
            "max_level": true,
            "rarity": 5,
            "awake": 1,
            "heroId": 339,
            "icon": "https://cbg-yys.res.netease.com//game_res/hero/339/339.png"
          },
          {
            "star": 6,
            "name": "少羽大天狗",
            "level": 40,
            "max_level": true,
            "rarity": 5,
            "awake": 1,
            "heroId": 315,
            "icon": "https://cbg-yys.res.netease.com//game_res/hero/315/315.png"
          },
          {
            "star": 6,
            "name": "赤影妖刀姬",
            "level": 40,
            "max_level": true,
            "rarity": 5,
            "awake": 1,
            "heroId": 328,
            "icon": "https://cbg-yys.res.netease.com//game_res/hero/328/328.png"
          },
          {
            "star": 6,
            "name": "烬天玉藻前",
            "level": 40,
            "max_level": true,
            "rarity": 5,
            "awake": 1,
            "heroId": 339,
            "icon": "https://cbg-yys.res.netease.com//game_res/hero/339/339.png"
          },
          {
            "star": 6,
            "name": "不知火",
            "level": 40,
            "max_level": true,
            "rarity": 4,
            "awake": 1,
            "heroId": 330,
            "icon": "https://cbg-yys.res.netease.com//game_res/hero/330/330.png"
          }
        ],
        "level_desc": "60级",
        "highlights": [],
        "desc_sumup": "SSR 29   六星式神 38   签到757天",
        "basic_attrs": [
          "SSR 29",
          "六星式神 38",
          "签到757天"
        ],
        "icon": "https://cbg-yys.res.netease.com//game_res/hero/339/339.png",
        "desc_sumup_short": "SSR 29   六星式神 38   签到757天"
      },
      "allow_urs_bargain": false,
      "expire_remain_seconds": 1203278,
      "serverid": 9,
      "icon": "https://cbg-yys.res.netease.com//game_res/hero/339/339.png",
      "game_ordersn": "202009112001616-9-3Q3L9NW7I21DF5",
      "platform_type": 1,
      "allow_bargain": false,
      "format_equip_name": "爱果果",
      "game_channel": "netease"
    },
    {
      "storage_type": 4,
      "tag": "latest",
      "collect_num": 0,
      "pass_fair_show": 0,
      "server_name": "暖风春穗",
      "level_desc": "60级",
      "highlights": [],
      "kindid": 1,
      "equip_level": 60,
      "tag_key": "{\"sort_key\": \"recommd\", \"tag\": \"latest\", \"sort_order\": \"\"}",
      "area_name": "全平台互通新区",
      "desc_sumup_short": "SSR 36   六星式神 16   签到621天",
      "equip_type": "0",
      "price": 79900,
      "other_info": {
        "top_heros": [
          {
            "star": 6,
            "name": "稻荷神御馔津",
            "level": 40,
            "max_level": true,
            "rarity": 5,
            "awake": 1,
            "heroId": 326,
            "icon": "https://cbg-yys.res.netease.com//game_res/hero/326/326.png"
          },
          {
            "star": 6,
            "name": "鬼王酒吞童子",
            "level": 40,
            "max_level": true,
            "rarity": 5,
            "awake": 1,
            "heroId": 341,
            "icon": "https://cbg-yys.res.netease.com//game_res/hero/341/341.png"
          },
          {
            "star": 6,
            "name": "烬天玉藻前",
            "level": 40,
            "max_level": true,
            "rarity": 5,
            "awake": 1,
            "heroId": 339,
            "icon": "https://cbg-yys.res.netease.com//game_res/hero/339/339.png"
          },
          {
            "star": 6,
            "name": "烬天玉藻前",
            "level": 40,
            "max_level": true,
            "rarity": 5,
            "awake": 1,
            "heroId": 339,
            "icon": "https://cbg-yys.res.netease.com//game_res/hero/339/339.png"
          },
          {
            "star": 6,
            "name": "炼狱茨木童子",
            "level": 40,
            "max_level": true,
            "rarity": 5,
            "awake": 1,
            "heroId": 322,
            "icon": "https://cbg-yys.res.netease.com//game_res/hero/322/322.png"
          }
        ],
        "level_desc": "60级",
        "highlights": [],
        "desc_sumup": "SSR 36   六星式神 16   签到621天",
        "basic_attrs": [
          "SSR 36",
          "六星式神 16",
          "签到621天"
        ],
        "icon": "https://cbg-yys.res.netease.com//game_res/hero/326/326.png",
        "desc_sumup_short": "SSR 36   六星式神 16   签到621天"
      },
      "allow_urs_bargain": false,
      "expire_remain_seconds": 1289623,
      "serverid": 24,
      "icon": "https://cbg-yys.res.netease.com//game_res/hero/326/326.png",
      "game_ordersn": "202009152001616-24-SBTGFDGMEIL6M",
      "platform_type": 2,
      "allow_bargain": false,
      "format_equip_name": "玉玉崽",
      "game_channel": "netease"
    },
    {
      "storage_type": 4,
      "tag": "latest",
      "collect_num": 43,
      "pass_fair_show": 1,
      "server_name": "雪之萤",
      "level_desc": "60级",
      "highlights": [],
      "kindid": 1,
      "equip_level": 60,
      "tag_key": "{\"sort_key\": \"recommd\", \"tag\": \"latest\", \"sort_order\": \"\"}",
      "area_name": "全平台互通新区",
      "desc_sumup_short": "SSR 20   六星式神 22   签到412天",
      "equip_type": "0",
      "price": 37500,
      "other_info": {
        "top_heros": [
          {
            "star": 6,
            "name": "稻荷神御馔津",
            "level": 40,
            "max_level": true,
            "rarity": 5,
            "awake": 1,
            "heroId": 326,
            "icon": "https://cbg-yys.res.netease.com//game_res/hero/326/326.png"
          },
          {
            "star": 6,
            "name": "炼狱茨木童子",
            "level": 40,
            "max_level": true,
            "rarity": 5,
            "awake": 1,
            "heroId": 322,
            "icon": "https://cbg-yys.res.netease.com//game_res/hero/322/322.png"
          },
          {
            "star": 6,
            "name": "辉夜姬",
            "level": 40,
            "max_level": true,
            "rarity": 4,
            "awake": 1,
            "heroId": 280,
            "icon": "https://cbg-yys.res.netease.com//game_res/hero/280/280.png"
          },
          {
            "star": 6,
            "name": "花鸟卷",
            "level": 40,
            "max_level": true,
            "rarity": 4,
            "awake": 1,
            "heroId": 279,
            "icon": "https://cbg-yys.res.netease.com//game_res/hero/279/279.png"
          },
          {
            "star": 6,
            "name": "大天狗",
            "level": 40,
            "max_level": true,
            "rarity": 4,
            "awake": 1,
            "heroId": 217,
            "icon": "https://cbg-yys.res.netease.com//game_res/hero/217/217.png"
          }
        ],
        "level_desc": "60级",
        "highlights": [],
        "desc_sumup": "SSR 20   六星式神 22   签到412天",
        "basic_attrs": [
          "SSR 20",
          "六星式神 22",
          "签到412天"
        ],
        "icon": "https://cbg-yys.res.netease.com//game_res/hero/326/326.png",
        "desc_sumup_short": "SSR 20   六星式神 22   签到412天"
      },
      "allow_urs_bargain": false,
      "expire_remain_seconds": 1203197,
      "serverid": 34,
      "icon": "https://cbg-yys.res.netease.com//game_res/hero/326/326.png",
      "game_ordersn": "202008051501616-34-UNI2UMUO5CKSK",
      "platform_type": 1,
      "allow_bargain": false,
      "format_equip_name": "小苏词",
      "game_channel": "netease"
    },
    {
      "storage_type": 4,
      "tag": "latest",
      "collect_num": 0,
      "pass_fair_show": 0,
      "server_name": "春之樱",
      "level_desc": "60级",
      "highlights": [
        "终极之巅"
      ],
      "kindid": 1,
      "equip_level": 60,
      "tag_key": "{\"sort_key\": \"recommd\", \"tag\": \"latest\", \"sort_order\": \"\"}",
      "area_name": "中国区-iOS",
      "desc_sumup_short": "SSR 21   六星式神 45   签到1027天",
      "equip_type": "0",
      "price": 89900,
      "other_info": {
        "top_heros": [
          {
            "star": 6,
            "name": "天剑韧心鬼切",
            "level": 40,
            "max_level": true,
            "rarity": 5,
            "awake": 1,
            "heroId": 343,
            "icon": "https://cbg-yys.res.netease.com//game_res/hero/343/343.png"
          },
          {
            "star": 6,
            "name": "聆海金鱼姬",
            "level": 40,
            "max_level": true,
            "rarity": 5,
            "awake": 1,
            "heroId": 346,
            "icon": "https://cbg-yys.res.netease.com//game_res/hero/346/346.png"
          },
          {
            "star": 6,
            "name": "烬天玉藻前",
            "level": 40,
            "max_level": true,
            "rarity": 5,
            "awake": 1,
            "heroId": 339,
            "icon": "https://cbg-yys.res.netease.com//game_res/hero/339/339.png"
          },
          {
            "star": 6,
            "name": "鬼王酒吞童子",
            "level": 40,
            "max_level": true,
            "rarity": 5,
            "awake": 1,
            "heroId": 341,
            "icon": "https://cbg-yys.res.netease.com//game_res/hero/341/341.png"
          },
          {
            "star": 6,
            "name": "稻荷神御馔津",
            "level": 40,
            "max_level": true,
            "rarity": 5,
            "awake": 1,
            "heroId": 326,
            "icon": "https://cbg-yys.res.netease.com//game_res/hero/326/326.png"
          }
        ],
        "level_desc": "60级",
        "highlights": [
          "终极之巅"
        ],
        "desc_sumup": "SSR 21   六星式神 45   签到1027天",
        "basic_attrs": [
          "SSR 21",
          "六星式神 45",
          "签到1027天"
        ],
        "icon": "https://cbg-yys.res.netease.com//game_res/hero/343/343.png",
        "desc_sumup_short": "SSR 21   六星式神 45   签到1027天"
      },
      "allow_urs_bargain": false,
      "expire_remain_seconds": 1289582,
      "serverid": 20,
      "icon": "https://cbg-yys.res.netease.com//game_res/hero/343/343.png",
      "game_ordersn": "202009151901616-20-PMVDJODRII1DV",
      "platform_type": 1,
      "allow_bargain": false,
      "format_equip_name": "与栀",
      "game_channel": "netease"
    },
    {
      "storage_type": 4,
      "tag": "latest",
      "collect_num": 1,
      "pass_fair_show": 0,
      "server_name": "一叶禅心",
      "level_desc": "60级",
      "highlights": [
        "京都之主",
        "雪月华庭",
        "暖春翠庭"
      ],
      "kindid": 1,
      "equip_level": 60,
      "tag_key": "{\"sort_key\": \"recommd\", \"tag\": \"latest\", \"sort_order\": \"\"}",
      "area_name": "全平台互通新区",
      "desc_sumup_short": "SSR 46   六星式神 39   签到452天",
      "equip_type": "0",
      "price": 134000,
      "other_info": {
        "top_heros": [
          {
            "star": 6,
            "name": "炼狱茨木童子",
            "level": 40,
            "max_level": true,
            "rarity": 5,
            "awake": 1,
            "heroId": 322,
            "icon": "https://cbg-yys.res.netease.com//game_res/hero/322/322.png"
          },
          {
            "star": 6,
            "name": "御怨般若",
            "level": 40,
            "max_level": true,
            "rarity": 5,
            "awake": 1,
            "heroId": 331,
            "icon": "https://cbg-yys.res.netease.com//game_res/hero/331/331.png"
          },
          {
            "star": 6,
            "name": "烬天玉藻前",
            "level": 40,
            "max_level": true,
            "rarity": 5,
            "awake": 1,
            "heroId": 339,
            "icon": "https://cbg-yys.res.netease.com//game_res/hero/339/339.png"
          },
          {
            "star": 6,
            "name": "苍风一目连",
            "level": 40,
            "max_level": true,
            "rarity": 5,
            "awake": 1,
            "heroId": 327,
            "icon": "https://cbg-yys.res.netease.com//game_res/hero/327/327.png"
          },
          {
            "star": 6,
            "name": "烬天玉藻前",
            "level": 40,
            "max_level": true,
            "rarity": 5,
            "awake": 1,
            "heroId": 339,
            "icon": "https://cbg-yys.res.netease.com//game_res/hero/339/339.png"
          }
        ],
        "level_desc": "60级",
        "highlights": [
          "京都之主",
          "雪月华庭",
          "暖春翠庭"
        ],
        "desc_sumup": "SSR 46   六星式神 39   签到452天",
        "basic_attrs": [
          "SSR 46",
          "六星式神 39",
          "签到452天"
        ],
        "icon": "https://cbg-yys.res.netease.com//game_res/hero/322/322.png",
        "desc_sumup_short": "SSR 46   六星式神 39   签到452天"
      },
      "allow_urs_bargain": false,
      "expire_remain_seconds": 1289580,
      "serverid": 38,
      "icon": "https://cbg-yys.res.netease.com//game_res/hero/322/322.png",
      "game_ordersn": "202009151901616-38-RBDAEXUKTKFZA",
      "platform_type": 2,
      "allow_bargain": false,
      "format_equip_name": "\t神\t\t仙\t",
      "game_channel": "netease"
    },
    {
      "storage_type": 4,
      "tag": "latest",
      "collect_num": 0,
      "pass_fair_show": 0,
      "server_name": "雪之萤",
      "level_desc": "60级",
      "highlights": [],
      "kindid": 1,
      "equip_level": 60,
      "tag_key": "{\"sort_key\": \"recommd\", \"tag\": \"latest\", \"sort_order\": \"\"}",
      "area_name": "全平台互通新区",
      "desc_sumup_short": "SSR 11   六星式神 3   签到218天",
      "equip_type": "0",
      "price": 13000,
      "other_info": {
        "top_heros": [
          {
            "star": 6,
            "name": "八岐大蛇",
            "level": 40,
            "max_level": true,
            "rarity": 4,
            "awake": 1,
            "heroId": 325,
            "icon": "https://cbg-yys.res.netease.com//game_res/hero/325/325.png"
          },
          {
            "star": 6,
            "name": "炼狱茨木童子",
            "level": 35,
            "max_level": false,
            "rarity": 5,
            "awake": 1,
            "heroId": 322,
            "icon": "https://cbg-yys.res.netease.com//game_res/hero/322/322.png"
          },
          {
            "star": 6,
            "name": "玉藻前",
            "level": 35,
            "max_level": false,
            "rarity": 4,
            "awake": 1,
            "heroId": 300,
            "icon": "https://cbg-yys.res.netease.com//game_res/hero/300/300.png"
          },
          {
            "star": 5,
            "name": "彼岸花",
            "level": 35,
            "max_level": false,
            "rarity": 4,
            "awake": 1,
            "heroId": 288,
            "icon": "https://cbg-yys.res.netease.com//game_res/hero/288/288.png"
          },
          {
            "star": 5,
            "name": "黑童子",
            "level": 33,
            "max_level": false,
            "rarity": 3,
            "awake": 1,
            "heroId": 277,
            "icon": "https://cbg-yys.res.netease.com//game_res/hero/277/277.png"
          }
        ],
        "level_desc": "60级",
        "highlights": [],
        "desc_sumup": "SSR 11   六星式神 3   签到218天",
        "basic_attrs": [
          "SSR 11",
          "六星式神 3",
          "签到218天"
        ],
        "icon": "https://cbg-yys.res.netease.com//game_res/hero/325/325.png",
        "desc_sumup_short": "SSR 11   六星式神 3   签到218天"
      },
      "allow_urs_bargain": false,
      "expire_remain_seconds": 1289578,
      "serverid": 34,
      "icon": "https://cbg-yys.res.netease.com//game_res/hero/325/325.png",
      "game_ordersn": "202009151901616-34-YZ0JPMI6UIKNQ",
      "platform_type": 2,
      "allow_bargain": false,
      "format_equip_name": "鵗",
      "game_channel": "netease"
    },
    {
      "storage_type": 4,
      "tag": "latest",
      "collect_num": 0,
      "pass_fair_show": 0,
      "server_name": "网易-相伴相随",
      "level_desc": "60级",
      "highlights": [
        "赤之流火"
      ],
      "kindid": 1,
      "equip_level": 60,
      "tag_key": "{\"sort_key\": \"recommd\", \"tag\": \"latest\", \"sort_order\": \"\"}",
      "area_name": "网易-双平台",
      "desc_sumup_short": "SSR 39   六星式神 39   签到947天",
      "equip_type": "0",
      "price": 100000,
      "other_info": {
        "top_heros": [
          {
            "star": 6,
            "name": "御怨般若",
            "level": 40,
            "max_level": true,
            "rarity": 5,
            "awake": 1,
            "heroId": 331,
            "icon": "https://cbg-yys.res.netease.com//game_res/hero/331/331.png"
          },
          {
            "star": 6,
            "name": "炼狱茨木童子",
            "level": 40,
            "max_level": true,
            "rarity": 5,
            "awake": 1,
            "heroId": 322,
            "icon": "https://cbg-yys.res.netease.com//game_res/hero/322/322.png"
          },
          {
            "star": 6,
            "name": "稻荷神御馔津",
            "level": 40,
            "max_level": true,
            "rarity": 5,
            "awake": 1,
            "heroId": 326,
            "icon": "https://cbg-yys.res.netease.com//game_res/hero/326/326.png"
          },
          {
            "star": 6,
            "name": "少羽大天狗",
            "level": 40,
            "max_level": true,
            "rarity": 5,
            "awake": 1,
            "heroId": 315,
            "icon": "https://cbg-yys.res.netease.com//game_res/hero/315/315.png"
          },
          {
            "star": 6,
            "name": "炼狱茨木童子",
            "level": 40,
            "max_level": true,
            "rarity": 5,
            "awake": 1,
            "heroId": 322,
            "icon": "https://cbg-yys.res.netease.com//game_res/hero/322/322.png"
          }
        ],
        "level_desc": "60级",
        "highlights": [
          "赤之流火"
        ],
        "desc_sumup": "SSR 39   六星式神 39   签到947天",
        "basic_attrs": [
          "SSR 39",
          "六星式神 39",
          "签到947天"
        ],
        "icon": "https://cbg-yys.res.netease.com//game_res/hero/331/331.png",
        "desc_sumup_short": "SSR 39   六星式神 39   签到947天"
      },
      "allow_urs_bargain": false,
      "expire_remain_seconds": 1289566,
      "serverid": 12,
      "icon": "https://cbg-yys.res.netease.com//game_res/hero/331/331.png",
      "game_ordersn": "202009151901616-12-JMIZP7LB41LX3",
      "platform_type": 2,
      "allow_bargain": false,
      "format_equip_name": "独饮一千秋",
      "game_channel": "netease"
    },
    {
      "storage_type": 4,
      "tag": "latest",
      "collect_num": 107,
      "pass_fair_show": 1,
      "server_name": "竹之幽",
      "level_desc": "60级",
      "highlights": [],
      "kindid": 1,
      "equip_level": 60,
      "tag_key": "{\"sort_key\": \"recommd\", \"tag\": \"latest\", \"sort_order\": \"\"}",
      "area_name": "中国区-iOS",
      "desc_sumup_short": "SSR 19   六星式神 8   签到262天",
      "equip_type": "0",
      "price": 55500,
      "other_info": {
        "top_heros": [
          {
            "star": 6,
            "name": "烬天玉藻前",
            "level": 40,
            "max_level": true,
            "rarity": 5,
            "awake": 1,
            "heroId": 339,
            "icon": "https://cbg-yys.res.netease.com//game_res/hero/339/339.png"
          },
          {
            "star": 6,
            "name": "炼狱茨木童子",
            "level": 40,
            "max_level": true,
            "rarity": 5,
            "awake": 1,
            "heroId": 322,
            "icon": "https://cbg-yys.res.netease.com//game_res/hero/322/322.png"
          },
          {
            "star": 6,
            "name": "骁浪荒川之主",
            "level": 40,
            "max_level": true,
            "rarity": 5,
            "awake": 1,
            "heroId": 334,
            "icon": "https://cbg-yys.res.netease.com//game_res/hero/334/334.png"
          },
          {
            "star": 6,
            "name": "少羽大天狗",
            "level": 40,
            "max_level": true,
            "rarity": 5,
            "awake": 1,
            "heroId": 315,
            "icon": "https://cbg-yys.res.netease.com//game_res/hero/315/315.png"
          },
          {
            "star": 6,
            "name": "茨木童子",
            "level": 40,
            "max_level": true,
            "rarity": 4,
            "awake": 1,
            "heroId": 265,
            "icon": "https://cbg-yys.res.netease.com//game_res/hero/265/265.png"
          }
        ],
        "level_desc": "60级",
        "highlights": [],
        "desc_sumup": "SSR 19   六星式神 8   签到262天",
        "basic_attrs": [
          "SSR 19",
          "六星式神 8",
          "签到262天"
        ],
        "icon": "https://cbg-yys.res.netease.com//game_res/hero/339/339.png",
        "desc_sumup_short": "SSR 19   六星式神 8   签到262天"
      },
      "allow_urs_bargain": false,
      "expire_remain_seconds": 1203162,
      "serverid": 22,
      "icon": "https://cbg-yys.res.netease.com//game_res/hero/339/339.png",
      "game_ordersn": "202009071101616-22-VLPLT34JRUGBA",
      "platform_type": 1,
      "allow_bargain": false,
      "format_equip_name": "58黑蛋3万勾",
      "game_channel": "netease"
    },
    {
      "storage_type": 4,
      "tag": "latest",
      "collect_num": 49,
      "pass_fair_show": 1,
      "server_name": "夜之月",
      "level_desc": "60级",
      "highlights": [
        "月见黑"
      ],
      "kindid": 1,
      "equip_level": 60,
      "tag_key": "{\"sort_key\": \"recommd\", \"tag\": \"latest\", \"sort_order\": \"\"}",
      "area_name": "中国区-iOS",
      "desc_sumup_short": "SSR 22   六星式神 14   签到547天",
      "equip_type": "0",
      "price": 34500,
      "other_info": {
        "top_heros": [
          {
            "star": 6,
            "name": "烬天玉藻前",
            "level": 40,
            "max_level": true,
            "rarity": 5,
            "awake": 1,
            "heroId": 339,
            "icon": "https://cbg-yys.res.netease.com//game_res/hero/339/339.png"
          },
          {
            "star": 6,
            "name": "少羽大天狗",
            "level": 40,
            "max_level": true,
            "rarity": 5,
            "awake": 1,
            "heroId": 315,
            "icon": "https://cbg-yys.res.netease.com//game_res/hero/315/315.png"
          },
          {
            "star": 6,
            "name": "赤影妖刀姬",
            "level": 40,
            "max_level": true,
            "rarity": 5,
            "awake": 1,
            "heroId": 328,
            "icon": "https://cbg-yys.res.netease.com//game_res/hero/328/328.png"
          },
          {
            "star": 6,
            "name": "泷夜叉姬",
            "level": 40,
            "max_level": true,
            "rarity": 4,
            "awake": 1,
            "heroId": 338,
            "icon": "https://cbg-yys.res.netease.com//game_res/hero/338/338.png"
          },
          {
            "star": 6,
            "name": "白藏主",
            "level": 40,
            "max_level": true,
            "rarity": 4,
            "awake": 1,
            "heroId": 316,
            "icon": "https://cbg-yys.res.netease.com//game_res/hero/316/316.png"
          }
        ],
        "level_desc": "60级",
        "highlights": [
          "月见黑"
        ],
        "desc_sumup": "SSR 22   六星式神 14   签到547天",
        "basic_attrs": [
          "SSR 22",
          "六星式神 14",
          "签到547天"
        ],
        "icon": "https://cbg-yys.res.netease.com//game_res/hero/339/339.png",
        "desc_sumup_short": "SSR 22   六星式神 14   签到547天"
      },
      "allow_urs_bargain": false,
      "expire_remain_seconds": 1203149,
      "serverid": 6,
      "icon": "https://cbg-yys.res.netease.com//game_res/hero/339/339.png",
      "game_ordersn": "202008281501616-6-NCYE6RS5EG2WTA",
      "platform_type": 1,
      "allow_bargain": false,
      "format_equip_name": "双烬潜力号",
      "game_channel": "netease"
    },
    {
      "storage_type": 4,
      "tag": "latest",
      "collect_num": 5,
      "pass_fair_show": 0,
      "server_name": "网易-结伴同游",
      "level_desc": "60级",
      "highlights": [],
      "kindid": 1,
      "equip_level": 60,
      "tag_key": "{\"sort_key\": \"recommd\", \"tag\": \"latest\", \"sort_order\": \"\"}",
      "area_name": "网易-双平台",
      "desc_sumup_short": "SSR 70   六星式神 43   签到1153天",
      "equip_type": "0",
      "price": 60000,
      "other_info": {
        "top_heros": [
          {
            "star": 6,
            "name": "炼狱茨木童子",
            "level": 40,
            "max_level": true,
            "rarity": 5,
            "awake": 1,
            "heroId": 322,
            "icon": "https://cbg-yys.res.netease.com//game_res/hero/322/322.png"
          },
          {
            "star": 6,
            "name": "苍风一目连",
            "level": 40,
            "max_level": true,
            "rarity": 5,
            "awake": 1,
            "heroId": 327,
            "icon": "https://cbg-yys.res.netease.com//game_res/hero/327/327.png"
          },
          {
            "star": 6,
            "name": "炼狱茨木童子",
            "level": 40,
            "max_level": true,
            "rarity": 5,
            "awake": 1,
            "heroId": 322,
            "icon": "https://cbg-yys.res.netease.com//game_res/hero/322/322.png"
          },
          {
            "star": 6,
            "name": "烬天玉藻前",
            "level": 40,
            "max_level": true,
            "rarity": 5,
            "awake": 1,
            "heroId": 339,
            "icon": "https://cbg-yys.res.netease.com//game_res/hero/339/339.png"
          },
          {
            "star": 6,
            "name": "少羽大天狗",
            "level": 40,
            "max_level": true,
            "rarity": 5,
            "awake": 1,
            "heroId": 315,
            "icon": "https://cbg-yys.res.netease.com//game_res/hero/315/315.png"
          }
        ],
        "level_desc": "60级",
        "highlights": [],
        "desc_sumup": "SSR 70   六星式神 43   签到1153天",
        "basic_attrs": [
          "SSR 70",
          "六星式神 43",
          "签到1153天"
        ],
        "icon": "https://cbg-yys.res.netease.com//game_res/hero/322/322.png",
        "desc_sumup_short": "SSR 70   六星式神 43   签到1153天"
      },
      "allow_urs_bargain": false,
      "expire_remain_seconds": 1254742,
      "serverid": 2,
      "icon": "https://cbg-yys.res.netease.com//game_res/hero/322/322.png",
      "game_ordersn": "202009151001616-2-Y0IFT146GQXA1Y",
      "platform_type": 1,
      "allow_bargain": false,
      "format_equip_name": "卡拉草莓",
      "game_channel": "netease"
    },
    {
      "storage_type": 4,
      "tag": "latest",
      "collect_num": 1,
      "pass_fair_show": 1,
      "server_name": "网易-携手同心",
      "level_desc": "60级",
      "highlights": [],
      "kindid": 1,
      "equip_level": 60,
      "tag_key": "{\"sort_key\": \"recommd\", \"tag\": \"latest\", \"sort_order\": \"\"}",
      "area_name": "网易-双平台",
      "desc_sumup_short": "SSR 30   六星式神 14   签到722天",
      "equip_type": "0",
      "price": 39000,
      "other_info": {
        "top_heros": [
          {
            "star": 6,
            "name": "鬼王酒吞童子",
            "level": 40,
            "max_level": true,
            "rarity": 5,
            "awake": 1,
            "heroId": 341,
            "icon": "https://cbg-yys.res.netease.com//game_res/hero/341/341.png"
          },
          {
            "star": 6,
            "name": "炼狱茨木童子",
            "level": 40,
            "max_level": true,
            "rarity": 5,
            "awake": 1,
            "heroId": 322,
            "icon": "https://cbg-yys.res.netease.com//game_res/hero/322/322.png"
          },
          {
            "star": 6,
            "name": "炼狱茨木童子",
            "level": 40,
            "max_level": true,
            "rarity": 5,
            "awake": 1,
            "heroId": 322,
            "icon": "https://cbg-yys.res.netease.com//game_res/hero/322/322.png"
          },
          {
            "star": 6,
            "name": "鬼童丸",
            "level": 40,
            "max_level": true,
            "rarity": 4,
            "awake": 1,
            "heroId": 345,
            "icon": "https://cbg-yys.res.netease.com//game_res/hero/345/345.png"
          },
          {
            "star": 6,
            "name": "花鸟卷",
            "level": 40,
            "max_level": true,
            "rarity": 4,
            "awake": 1,
            "heroId": 279,
            "icon": "https://cbg-yys.res.netease.com//game_res/hero/279/279.png"
          }
        ],
        "level_desc": "60级",
        "highlights": [],
        "desc_sumup": "SSR 30   六星式神 14   签到722天",
        "basic_attrs": [
          "SSR 30",
          "六星式神 14",
          "签到722天"
        ],
        "icon": "https://cbg-yys.res.netease.com//game_res/hero/341/341.png",
        "desc_sumup_short": "SSR 30   六星式神 14   签到722天"
      },
      "allow_urs_bargain": true,
      "expire_remain_seconds": 1203101,
      "serverid": 17,
      "icon": "https://cbg-yys.res.netease.com//game_res/hero/341/341.png",
      "game_ordersn": "202008301901616-17-1PBIAJARNNQMX",
      "platform_type": 2,
      "allow_bargain": true,
      "format_equip_name": "说什么都晚了",
      "game_channel": "netease"
    },
    {
      "storage_type": 4,
      "tag": "latest",
      "collect_num": 8,
      "pass_fair_show": 1,
      "server_name": "网易-两情相悦",
      "level_desc": "60级",
      "highlights": [
        "终极之巅"
      ],
      "kindid": 1,
      "equip_level": 60,
      "tag_key": "{\"sort_key\": \"recommd\", \"tag\": \"latest\", \"sort_order\": \"\"}",
      "area_name": "网易-双平台",
      "desc_sumup_short": "SSR 39   六星式神 50   签到817天",
      "equip_type": "0",
      "price": 85000,
      "other_info": {
        "top_heros": [
          {
            "star": 6,
            "name": "炼狱茨木童子",
            "level": 40,
            "max_level": true,
            "rarity": 5,
            "awake": 1,
            "heroId": 322,
            "icon": "https://cbg-yys.res.netease.com//game_res/hero/322/322.png"
          },
          {
            "star": 6,
            "name": "少羽大天狗",
            "level": 40,
            "max_level": true,
            "rarity": 5,
            "awake": 1,
            "heroId": 315,
            "icon": "https://cbg-yys.res.netease.com//game_res/hero/315/315.png"
          },
          {
            "star": 6,
            "name": "赤影妖刀姬",
            "level": 40,
            "max_level": true,
            "rarity": 5,
            "awake": 1,
            "heroId": 328,
            "icon": "https://cbg-yys.res.netease.com//game_res/hero/328/328.png"
          },
          {
            "star": 6,
            "name": "聆海金鱼姬",
            "level": 40,
            "max_level": true,
            "rarity": 5,
            "awake": 1,
            "heroId": 346,
            "icon": "https://cbg-yys.res.netease.com//game_res/hero/346/346.png"
          },
          {
            "star": 6,
            "name": "御怨般若",
            "level": 40,
            "max_level": true,
            "rarity": 5,
            "awake": 1,
            "heroId": 331,
            "icon": "https://cbg-yys.res.netease.com//game_res/hero/331/331.png"
          }
        ],
        "level_desc": "60级",
        "highlights": [
          "终极之巅"
        ],
        "desc_sumup": "SSR 39   六星式神 50   签到817天",
        "basic_attrs": [
          "SSR 39",
          "六星式神 50",
          "签到817天"
        ],
        "icon": "https://cbg-yys.res.netease.com//game_res/hero/322/322.png",
        "desc_sumup_short": "SSR 39   六星式神 50   签到817天"
      },
      "allow_urs_bargain": true,
      "expire_remain_seconds": 1203090,
      "serverid": 3,
      "icon": "https://cbg-yys.res.netease.com//game_res/hero/322/322.png",
      "game_ordersn": "202005131001616-3-SQFDNU3QXCDQCZ",
      "platform_type": 2,
      "allow_bargain": true,
      "format_equip_name": "呆桃",
      "game_channel": "netease"
    }
  ],
  "pager": {
    "cur_page": 22,
    "total_pages": 100
  }
}