{
  "status": 1,
  "server_time": 1600784281715,
  "order_field": "selling_time",
  "order_headers": [
    {
      "field": "selling_time",
      "direction": [
        "DESC"
      ],
      "name": "最新"
    },
    {
      "field": "recommd",
      "direction": [],
      "name": "人气"
    },
    {
      "field": "price",
      "direction": [
        "DESC",
        "ASC"
      ],
      "name": "价格"
    }
  ],
  "order_direction": "DESC",
  "paging": {
    "is_last_page": false
  },
  "result": [
    {
      "storage_type": 4,
      "tag": "latest",
      "collect_num": 3,
      "pass_fair_show": 1,
      "server_name": "春之樱",
      "level_desc": "60级",
      "highlights": [],
      "kindid": 1,
      "equip_level": 60,
      "tag_key": "{\"sort_key\": \"recommd\", \"tag\": \"latest\", \"sort_order\": \"\"}",
      "area_name": "中国区-iOS",
      "desc_sumup_short": "SSR 12   六星式神 12   签到351天",
      "equip_type": "0",
      "price": 20000,
      "other_info": {
        "top_heros": [
          {
            "star": 6,
            "name": "炼狱茨木童子",
            "level": 40,
            "max_level": true,
            "rarity": 5,
            "awake": 1,
            "heroId": 322,
            "icon": "https://cbg-yys.res.netease.com//game_res/hero/322/322.png"
          },
          {
            "star": 6,
            "name": "少羽大天狗",
            "level": 40,
            "max_level": true,
            "rarity": 5,
            "awake": 1,
            "heroId": 315,
            "icon": "https://cbg-yys.res.netease.com//game_res/hero/315/315.png"
          },
          {
            "star": 6,
            "name": "苍风一目连",
            "level": 40,
            "max_level": true,
            "rarity": 5,
            "awake": 1,
            "heroId": 327,
            "icon": "https://cbg-yys.res.netease.com//game_res/hero/327/327.png"
          },
          {
            "star": 6,
            "name": "八岐大蛇",
            "level": 40,
            "max_level": true,
            "rarity": 4,
            "awake": 1,
            "heroId": 325,
            "icon": "https://cbg-yys.res.netease.com//game_res/hero/325/325.png"
          },
          {
            "star": 6,
            "name": "黑崎一护",
            "level": 40,
            "max_level": true,
            "rarity": 4,
            "awake": 1,
            "heroId": 337,
            "icon": "https://cbg-yys.res.netease.com//game_res/hero/337/337.png"
          }
        ],
        "level_desc": "60级",
        "highlights": [],
        "desc_sumup": "SSR 12   六星式神 12   签到351天",
        "basic_attrs": [
          "SSR 12",
          "六星式神 12",
          "签到351天"
        ],
        "icon": "https://cbg-yys.res.netease.com//game_res/hero/322/322.png",
        "desc_sumup_short": "SSR 12   六星式神 12   签到351天"
      },
      "allow_urs_bargain": false,
      "expire_remain_seconds": 1200373,
      "serverid": 20,
      "icon": "https://cbg-yys.res.netease.com//game_res/hero/322/322.png",
      "game_ordersn": "202004200001616-20-3ZGS7EKLSJ1KP",
      "platform_type": 1,
      "allow_bargain": false,
      "format_equip_name": "瞳邙",
      "game_channel": "netease"
    },
    {
      "storage_type": 4,
      "tag": "latest",
      "collect_num": 5,
      "pass_fair_show": 0,
      "server_name": "网易-心意相通",
      "level_desc": "60级",
      "highlights": [
        "雪月华庭",
        "赤之流火"
      ],
      "kindid": 1,
      "equip_level": 60,
      "tag_key": "{\"sort_key\": \"recommd\", \"tag\": \"latest\", \"sort_order\": \"\"}",
      "area_name": "网易-双平台",
      "desc_sumup_short": "SSR 84   六星式神 84   签到1308天",
      "equip_type": "0",
      "price": 179900,
      "other_info": {
        "top_heros": [
          {
            "star": 6,
            "name": "少羽大天狗",
            "level": 40,
            "max_level": true,
            "rarity": 5,
            "awake": 1,
            "heroId": 315,
            "icon": "https://cbg-yys.res.netease.com//game_res/hero/315/315.png"
          },
          {
            "star": 6,
            "name": "稻荷神御馔津",
            "level": 40,
            "max_level": true,
            "rarity": 5,
            "awake": 1,
            "heroId": 326,
            "icon": "https://cbg-yys.res.netease.com//game_res/hero/326/326.png"
          },
          {
            "star": 6,
            "name": "鬼王酒吞童子",
            "level": 40,
            "max_level": true,
            "rarity": 5,
            "awake": 1,
            "heroId": 341,
            "icon": "https://cbg-yys.res.netease.com//game_res/hero/341/341.png"
          },
          {
            "star": 6,
            "name": "聆海金鱼姬",
            "level": 40,
            "max_level": true,
            "rarity": 5,
            "awake": 1,
            "heroId": 346,
            "icon": "https://cbg-yys.res.netease.com//game_res/hero/346/346.png"
          },
          {
            "star": 6,
            "name": "炼狱茨木童子",
            "level": 40,
            "max_level": true,
            "rarity": 5,
            "awake": 1,
            "heroId": 322,
            "icon": "https://cbg-yys.res.netease.com//game_res/hero/322/322.png"
          }
        ],
        "level_desc": "60级",
        "highlights": [
          "雪月华庭",
          "赤之流火"
        ],
        "desc_sumup": "SSR 84   六星式神 84   签到1308天",
        "basic_attrs": [
          "SSR 84",
          "六星式神 84",
          "签到1308天"
        ],
        "icon": "https://cbg-yys.res.netease.com//game_res/hero/315/315.png",
        "desc_sumup_short": "SSR 84   六星式神 84   签到1308天"
      },
      "allow_urs_bargain": false,
      "expire_remain_seconds": 1286752,
      "serverid": 10,
      "icon": "https://cbg-yys.res.netease.com//game_res/hero/315/315.png",
      "game_ordersn": "202009151901616-10-PHTUREEHJQZ59",
      "platform_type": 2,
      "allow_bargain": false,
      "format_equip_name": "杭州周杰伦",
      "game_channel": "netease"
    },
    {
      "storage_type": 4,
      "tag": "latest",
      "collect_num": 21,
      "pass_fair_show": 0,
      "server_name": "网易-两情相悦",
      "level_desc": "60级",
      "highlights": [
        "月见黑"
      ],
      "kindid": 1,
      "equip_level": 60,
      "tag_key": "{\"sort_key\": \"recommd\", \"tag\": \"latest\", \"sort_order\": \"\"}",
      "area_name": "网易-双平台",
      "desc_sumup_short": "SSR 38   六星式神 32   签到847天",
      "equip_type": "0",
      "price": 17400,
      "other_info": {
        "top_heros": [
          {
            "star": 6,
            "name": "烬天玉藻前",
            "level": 40,
            "max_level": true,
            "rarity": 5,
            "awake": 1,
            "heroId": 339,
            "icon": "https://cbg-yys.res.netease.com//game_res/hero/339/339.png"
          },
          {
            "star": 6,
            "name": "御怨般若",
            "level": 40,
            "max_level": true,
            "rarity": 5,
            "awake": 1,
            "heroId": 331,
            "icon": "https://cbg-yys.res.netease.com//game_res/hero/331/331.png"
          },
          {
            "star": 6,
            "name": "烬天玉藻前",
            "level": 40,
            "max_level": true,
            "rarity": 5,
            "awake": 1,
            "heroId": 339,
            "icon": "https://cbg-yys.res.netease.com//game_res/hero/339/339.png"
          },
          {
            "star": 6,
            "name": "稻荷神御馔津",
            "level": 40,
            "max_level": true,
            "rarity": 5,
            "awake": 1,
            "heroId": 326,
            "icon": "https://cbg-yys.res.netease.com//game_res/hero/326/326.png"
          },
          {
            "star": 6,
            "name": "烬天玉藻前",
            "level": 40,
            "max_level": true,
            "rarity": 5,
            "awake": 1,
            "heroId": 339,
            "icon": "https://cbg-yys.res.netease.com//game_res/hero/339/339.png"
          }
        ],
        "level_desc": "60级",
        "highlights": [
          "月见黑"
        ],
        "desc_sumup": "SSR 38   六星式神 32   签到847天",
        "basic_attrs": [
          "SSR 38",
          "六星式神 32",
          "签到847天"
        ],
        "icon": "https://cbg-yys.res.netease.com//game_res/hero/339/339.png",
        "desc_sumup_short": "SSR 38   六星式神 32   签到847天"
      },
      "allow_urs_bargain": false,
      "expire_remain_seconds": 1286703,
      "serverid": 3,
      "icon": "https://cbg-yys.res.netease.com//game_res/hero/339/339.png",
      "game_ordersn": "202009130001616-3-D5ERTZXNAI4M8A",
      "platform_type": 1,
      "allow_bargain": false,
      "format_equip_name": "三烬资源多仔细看",
      "game_channel": "netease"
    },
    {
      "storage_type": 4,
      "tag": "latest",
      "collect_num": 1,
      "pass_fair_show": 1,
      "server_name": "少时之约",
      "level_desc": "46级",
      "highlights": [
        "雪月华庭",
        "赤之流火"
      ],
      "kindid": 1,
      "equip_level": 46,
      "tag_key": "{\"sort_key\": \"recommd\", \"tag\": \"latest\", \"sort_order\": \"\"}",
      "area_name": "全平台互通新区",
      "desc_sumup_short": "SSR 28   六星式神 12   签到321天",
      "equip_type": "0",
      "price": 48000,
      "other_info": {
        "top_heros": [
          {
            "star": 6,
            "name": "烬天玉藻前",
            "level": 40,
            "max_level": true,
            "rarity": 5,
            "awake": 1,
            "heroId": 339,
            "icon": "https://cbg-yys.res.netease.com//game_res/hero/339/339.png"
          },
          {
            "star": 6,
            "name": "鬼王酒吞童子",
            "level": 40,
            "max_level": true,
            "rarity": 5,
            "awake": 1,
            "heroId": 341,
            "icon": "https://cbg-yys.res.netease.com//game_res/hero/341/341.png"
          },
          {
            "star": 6,
            "name": "白藏主",
            "level": 40,
            "max_level": true,
            "rarity": 4,
            "awake": 1,
            "heroId": 316,
            "icon": "https://cbg-yys.res.netease.com//game_res/hero/316/316.png"
          },
          {
            "star": 6,
            "name": "两面佛",
            "level": 40,
            "max_level": true,
            "rarity": 4,
            "awake": 1,
            "heroId": 258,
            "icon": "https://cbg-yys.res.netease.com//game_res/hero/258/258.png"
          },
          {
            "star": 6,
            "name": "不知火",
            "level": 40,
            "max_level": true,
            "rarity": 4,
            "awake": 1,
            "heroId": 330,
            "icon": "https://cbg-yys.res.netease.com//game_res/hero/330/330.png"
          }
        ],
        "level_desc": "46级",
        "highlights": [
          "雪月华庭",
          "赤之流火"
        ],
        "desc_sumup": "SSR 28   六星式神 12   签到321天",
        "basic_attrs": [
          "SSR 28",
          "六星式神 12",
          "签到321天"
        ],
        "icon": "https://cbg-yys.res.netease.com//game_res/hero/339/339.png",
        "desc_sumup_short": "SSR 28   六星式神 12   签到321天"
      },
      "allow_urs_bargain": false,
      "expire_remain_seconds": 1200283,
      "serverid": 42,
      "icon": "https://cbg-yys.res.netease.com//game_res/hero/339/339.png",
      "game_ordersn": "202009141401616-42-TCS9W5VJHXIKO",
      "platform_type": 2,
      "allow_bargain": false,
      "format_equip_name": "霓虹灯下影",
      "game_channel": "netease"
    },
    {
      "storage_type": 4,
      "tag": "latest",
      "collect_num": 0,
      "pass_fair_show": 1,
      "server_name": "八岐魅影",
      "level_desc": "60级",
      "highlights": [],
      "kindid": 1,
      "equip_level": 60,
      "tag_key": "{\"sort_key\": \"recommd\", \"tag\": \"latest\", \"sort_order\": \"\"}",
      "area_name": "全平台互通新区",
      "desc_sumup_short": "SSR 15   六星式神 8   签到90天",
      "equip_type": "0",
      "price": 35000,
      "other_info": {
        "top_heros": [
          {
            "star": 6,
            "name": "炼狱茨木童子",
            "level": 40,
            "max_level": true,
            "rarity": 5,
            "awake": 1,
            "heroId": 322,
            "icon": "https://cbg-yys.res.netease.com//game_res/hero/322/322.png"
          },
          {
            "star": 6,
            "name": "鬼切",
            "level": 40,
            "max_level": true,
            "rarity": 4,
            "awake": 1,
            "heroId": 312,
            "icon": "https://cbg-yys.res.netease.com//game_res/hero/312/312.png"
          },
          {
            "star": 6,
            "name": "玉藻前",
            "level": 40,
            "max_level": true,
            "rarity": 4,
            "awake": 1,
            "heroId": 300,
            "icon": "https://cbg-yys.res.netease.com//game_res/hero/300/300.png"
          },
          {
            "star": 6,
            "name": "大天狗",
            "level": 40,
            "max_level": true,
            "rarity": 4,
            "awake": 1,
            "heroId": 217,
            "icon": "https://cbg-yys.res.netease.com//game_res/hero/217/217.png"
          },
          {
            "star": 6,
            "name": "八岐大蛇",
            "level": 40,
            "max_level": true,
            "rarity": 4,
            "awake": 1,
            "heroId": 325,
            "icon": "https://cbg-yys.res.netease.com//game_res/hero/325/325.png"
          }
        ],
        "level_desc": "60级",
        "highlights": [],
        "desc_sumup": "SSR 15   六星式神 8   签到90天",
        "basic_attrs": [
          "SSR 15",
          "六星式神 8",
          "签到90天"
        ],
        "icon": "https://cbg-yys.res.netease.com//game_res/hero/322/322.png",
        "desc_sumup_short": "SSR 15   六星式神 8   签到90天"
      },
      "allow_urs_bargain": true,
      "expire_remain_seconds": 249877,
      "serverid": 45,
      "icon": "https://cbg-yys.res.netease.com//game_res/hero/322/322.png",
      "game_ordersn": "202009030001616-45-GZB0GKHGKZW5G",
      "platform_type": 2,
      "allow_bargain": true,
      "format_equip_name": "小虎哥丶",
      "game_channel": "netease"
    },
    {
      "storage_type": 4,
      "tag": "latest",
      "collect_num": 0,
      "pass_fair_show": 0,
      "server_name": "携手共度",
      "level_desc": "60级",
      "highlights": [],
      "kindid": 1,
      "equip_level": 60,
      "tag_key": "{\"sort_key\": \"recommd\", \"tag\": \"latest\", \"sort_order\": \"\"}",
      "area_name": "全平台互通新区",
      "desc_sumup_short": "SSR 40   六星式神 47   签到808天",
      "equip_type": "0",
      "price": 100000,
      "other_info": {
        "top_heros": [
          {
            "star": 6,
            "name": "鬼王酒吞童子",
            "level": 40,
            "max_level": true,
            "rarity": 5,
            "awake": 1,
            "heroId": 341,
            "icon": "https://cbg-yys.res.netease.com//game_res/hero/341/341.png"
          },
          {
            "star": 6,
            "name": "炼狱茨木童子",
            "level": 40,
            "max_level": true,
            "rarity": 5,
            "awake": 1,
            "heroId": 322,
            "icon": "https://cbg-yys.res.netease.com//game_res/hero/322/322.png"
          },
          {
            "star": 6,
            "name": "御怨般若",
            "level": 40,
            "max_level": true,
            "rarity": 5,
            "awake": 1,
            "heroId": 331,
            "icon": "https://cbg-yys.res.netease.com//game_res/hero/331/331.png"
          },
          {
            "star": 6,
            "name": "稻荷神御馔津",
            "level": 40,
            "max_level": true,
            "rarity": 5,
            "awake": 1,
            "heroId": 326,
            "icon": "https://cbg-yys.res.netease.com//game_res/hero/326/326.png"
          },
          {
            "star": 6,
            "name": "聆海金鱼姬",
            "level": 40,
            "max_level": true,
            "rarity": 5,
            "awake": 1,
            "heroId": 346,
            "icon": "https://cbg-yys.res.netease.com//game_res/hero/346/346.png"
          }
        ],
        "level_desc": "60级",
        "highlights": [],
        "desc_sumup": "SSR 40   六星式神 47   签到808天",
        "basic_attrs": [
          "SSR 40",
          "六星式神 47",
          "签到808天"
        ],
        "icon": "https://cbg-yys.res.netease.com//game_res/hero/341/341.png",
        "desc_sumup_short": "SSR 40   六星式神 47   签到808天"
      },
      "allow_urs_bargain": false,
      "expire_remain_seconds": 1286635,
      "serverid": 5,
      "icon": "https://cbg-yys.res.netease.com//game_res/hero/341/341.png",
      "game_ordersn": "202009151901616-5-D6U7O0M0P2VINA",
      "platform_type": 1,
      "allow_bargain": false,
      "format_equip_name": "是落星星呀",
      "game_channel": "netease"
    },
    {
      "storage_type": 4,
      "tag": "latest",
      "collect_num": 0,
      "pass_fair_show": 1,
      "server_name": "暖风春穗",
      "level_desc": "60级",
      "highlights": [
        "终极之巅"
      ],
      "kindid": 1,
      "equip_level": 60,
      "tag_key": "{\"sort_key\": \"recommd\", \"tag\": \"latest\", \"sort_order\": \"\"}",
      "area_name": "全平台互通新区",
      "desc_sumup_short": "SSR 62   六星式神 58   签到883天",
      "equip_type": "0",
      "price": 200000,
      "other_info": {
        "top_heros": [
          {
            "star": 6,
            "name": "少羽大天狗",
            "level": 40,
            "max_level": true,
            "rarity": 5,
            "awake": 1,
            "heroId": 315,
            "icon": "https://cbg-yys.res.netease.com//game_res/hero/315/315.png"
          },
          {
            "star": 6,
            "name": "烬天玉藻前",
            "level": 40,
            "max_level": true,
            "rarity": 5,
            "awake": 1,
            "heroId": 339,
            "icon": "https://cbg-yys.res.netease.com//game_res/hero/339/339.png"
          },
          {
            "star": 6,
            "name": "聆海金鱼姬",
            "level": 40,
            "max_level": true,
            "rarity": 5,
            "awake": 1,
            "heroId": 346,
            "icon": "https://cbg-yys.res.netease.com//game_res/hero/346/346.png"
          },
          {
            "star": 6,
            "name": "炼狱茨木童子",
            "level": 40,
            "max_level": true,
            "rarity": 5,
            "awake": 1,
            "heroId": 322,
            "icon": "https://cbg-yys.res.netease.com//game_res/hero/322/322.png"
          },
          {
            "star": 6,
            "name": "烬天玉藻前",
            "level": 40,
            "max_level": true,
            "rarity": 5,
            "awake": 1,
            "heroId": 339,
            "icon": "https://cbg-yys.res.netease.com//game_res/hero/339/339.png"
          }
        ],
        "level_desc": "60级",
        "highlights": [
          "终极之巅"
        ],
        "desc_sumup": "SSR 62   六星式神 58   签到883天",
        "basic_attrs": [
          "SSR 62",
          "六星式神 58",
          "签到883天"
        ],
        "icon": "https://cbg-yys.res.netease.com//game_res/hero/315/315.png",
        "desc_sumup_short": "SSR 62   六星式神 58   签到883天"
      },
      "allow_urs_bargain": false,
      "expire_remain_seconds": 1200228,
      "serverid": 24,
      "icon": "https://cbg-yys.res.netease.com//game_res/hero/315/315.png",
      "game_ordersn": "202008311901616-24-CPZJDZ3AOYZFO",
      "platform_type": 2,
      "allow_bargain": false,
      "format_equip_name": "大鱼丸干掉了鬼吞",
      "game_channel": "netease"
    },
    {
      "storage_type": 4,
      "tag": "latest",
      "collect_num": 3,
      "pass_fair_show": 0,
      "server_name": "一叶禅心",
      "level_desc": "60级",
      "highlights": [],
      "kindid": 1,
      "equip_level": 60,
      "tag_key": "{\"sort_key\": \"recommd\", \"tag\": \"latest\", \"sort_order\": \"\"}",
      "area_name": "全平台互通新区",
      "desc_sumup_short": "SSR 13   六星式神 6   签到72天",
      "equip_type": "0",
      "price": 12500,
      "other_info": {
        "top_heros": [
          {
            "star": 6,
            "name": "炼狱茨木童子",
            "level": 40,
            "max_level": true,
            "rarity": 5,
            "awake": 1,
            "heroId": 322,
            "icon": "https://cbg-yys.res.netease.com//game_res/hero/322/322.png"
          },
          {
            "star": 6,
            "name": "大天狗",
            "level": 40,
            "max_level": true,
            "rarity": 4,
            "awake": 1,
            "heroId": 217,
            "icon": "https://cbg-yys.res.netease.com//game_res/hero/217/217.png"
          },
          {
            "star": 6,
            "name": "大天狗",
            "level": 40,
            "max_level": true,
            "rarity": 4,
            "awake": 1,
            "heroId": 217,
            "icon": "https://cbg-yys.res.netease.com//game_res/hero/217/217.png"
          },
          {
            "star": 6,
            "name": "玉藻前",
            "level": 40,
            "max_level": true,
            "rarity": 4,
            "awake": 1,
            "heroId": 300,
            "icon": "https://cbg-yys.res.netease.com//game_res/hero/300/300.png"
          },
          {
            "star": 6,
            "name": "酒吞童子",
            "level": 40,
            "max_level": true,
            "rarity": 4,
            "awake": 1,
            "heroId": 219,
            "icon": "https://cbg-yys.res.netease.com//game_res/hero/219/219.png"
          }
        ],
        "level_desc": "60级",
        "highlights": [],
        "desc_sumup": "SSR 13   六星式神 6   签到72天",
        "basic_attrs": [
          "SSR 13",
          "六星式神 6",
          "签到72天"
        ],
        "icon": "https://cbg-yys.res.netease.com//game_res/hero/322/322.png",
        "desc_sumup_short": "SSR 13   六星式神 6   签到72天"
      },
      "allow_urs_bargain": false,
      "expire_remain_seconds": 1286553,
      "serverid": 38,
      "icon": "https://cbg-yys.res.netease.com//game_res/hero/322/322.png",
      "game_ordersn": "202009151901616-38-ICQY5SCDNBARB",
      "platform_type": 2,
      "allow_bargain": false,
      "format_equip_name": "柠檬酸酸鼠",
      "game_channel": "netease"
    },
    {
      "storage_type": 4,
      "tag": "latest",
      "collect_num": 0,
      "pass_fair_show": 1,
      "server_name": "网易-结伴同游",
      "level_desc": "60级",
      "highlights": [
        "黑晴明"
      ],
      "kindid": 1,
      "equip_level": 60,
      "tag_key": "{\"sort_key\": \"recommd\", \"tag\": \"latest\", \"sort_order\": \"\"}",
      "area_name": "网易-双平台",
      "desc_sumup_short": "SSR 57   六星式神 50   签到1281天",
      "equip_type": "0",
      "price": 185000,
      "other_info": {
        "top_heros": [
          {
            "star": 6,
            "name": "炼狱茨木童子",
            "level": 40,
            "max_level": true,
            "rarity": 5,
            "awake": 1,
            "heroId": 322,
            "icon": "https://cbg-yys.res.netease.com//game_res/hero/322/322.png"
          },
          {
            "star": 6,
            "name": "鬼王酒吞童子",
            "level": 40,
            "max_level": true,
            "rarity": 5,
            "awake": 1,
            "heroId": 341,
            "icon": "https://cbg-yys.res.netease.com//game_res/hero/341/341.png"
          },
          {
            "star": 6,
            "name": "烬天玉藻前",
            "level": 40,
            "max_level": true,
            "rarity": 5,
            "awake": 1,
            "heroId": 339,
            "icon": "https://cbg-yys.res.netease.com//game_res/hero/339/339.png"
          },
          {
            "star": 6,
            "name": "少羽大天狗",
            "level": 40,
            "max_level": true,
            "rarity": 5,
            "awake": 1,
            "heroId": 315,
            "icon": "https://cbg-yys.res.netease.com//game_res/hero/315/315.png"
          },
          {
            "star": 6,
            "name": "炼狱茨木童子",
            "level": 40,
            "max_level": true,
            "rarity": 5,
            "awake": 1,
            "heroId": 322,
            "icon": "https://cbg-yys.res.netease.com//game_res/hero/322/322.png"
          }
        ],
        "level_desc": "60级",
        "highlights": [
          "黑晴明"
        ],
        "desc_sumup": "SSR 57   六星式神 50   签到1281天",
        "basic_attrs": [
          "SSR 57",
          "六星式神 50",
          "签到1281天"
        ],
        "icon": "https://cbg-yys.res.netease.com//game_res/hero/322/322.png",
        "desc_sumup_short": "SSR 57   六星式神 50   签到1281天"
      },
      "allow_urs_bargain": true,
      "expire_remain_seconds": 1200138,
      "serverid": 2,
      "icon": "https://cbg-yys.res.netease.com//game_res/hero/322/322.png",
      "game_ordersn": "202008301501616-2-AHXIJDHB3TXF0A",
      "platform_type": 1,
      "allow_bargain": true,
      "format_equip_name": "何时明月",
      "game_channel": "netease"
    },
    {
      "storage_type": 4,
      "tag": "latest",
      "collect_num": 4,
      "pass_fair_show": 0,
      "server_name": "依偎相守",
      "level_desc": "60级",
      "highlights": [],
      "kindid": 1,
      "equip_level": 60,
      "tag_key": "{\"sort_key\": \"recommd\", \"tag\": \"latest\", \"sort_order\": \"\"}",
      "area_name": "全平台互通新区",
      "desc_sumup_short": "SSR 82   六星式神 33   签到850天",
      "equip_type": "0",
      "price": 100000,
      "other_info": {
        "top_heros": [
          {
            "star": 6,
            "name": "缚骨清姬",
            "level": 40,
            "max_level": true,
            "rarity": 5,
            "awake": 1,
            "heroId": 352,
            "icon": "https://cbg-yys.res.netease.com//game_res/hero/352/352.png"
          },
          {
            "star": 6,
            "name": "烬天玉藻前",
            "level": 40,
            "max_level": true,
            "rarity": 5,
            "awake": 1,
            "heroId": 339,
            "icon": "https://cbg-yys.res.netease.com//game_res/hero/339/339.png"
          },
          {
            "star": 6,
            "name": "鬼王酒吞童子",
            "level": 40,
            "max_level": true,
            "rarity": 5,
            "awake": 1,
            "heroId": 341,
            "icon": "https://cbg-yys.res.netease.com//game_res/hero/341/341.png"
          },
          {
            "star": 6,
            "name": "烬天玉藻前",
            "level": 40,
            "max_level": true,
            "rarity": 5,
            "awake": 1,
            "heroId": 339,
            "icon": "https://cbg-yys.res.netease.com//game_res/hero/339/339.png"
          },
          {
            "star": 6,
            "name": "少羽大天狗",
            "level": 40,
            "max_level": true,
            "rarity": 5,
            "awake": 1,
            "heroId": 315,
            "icon": "https://cbg-yys.res.netease.com//game_res/hero/315/315.png"
          }
        ],
        "level_desc": "60级",
        "highlights": [],
        "desc_sumup": "SSR 82   六星式神 33   签到850天",
        "basic_attrs": [
          "SSR 82",
          "六星式神 33",
          "签到850天"
        ],
        "icon": "https://cbg-yys.res.netease.com//game_res/hero/352/352.png",
        "desc_sumup_short": "SSR 82   六星式神 33   签到850天"
      },
      "allow_urs_bargain": false,
      "expire_remain_seconds": 1286512,
      "serverid": 15,
      "icon": "https://cbg-yys.res.netease.com//game_res/hero/352/352.png",
      "game_ordersn": "202009151901616-15-V1BNZRGCOK9GY",
      "platform_type": 2,
      "allow_bargain": false,
      "format_equip_name": "挖土21s真全图",
      "game_channel": "netease"
    },
    {
      "storage_type": 4,
      "tag": "latest",
      "collect_num": 8,
      "pass_fair_show": 0,
      "server_name": "网易-心意相通",
      "level_desc": "60级",
      "highlights": [],
      "kindid": 1,
      "equip_level": 60,
      "tag_key": "{\"sort_key\": \"recommd\", \"tag\": \"latest\", \"sort_order\": \"\"}",
      "area_name": "网易-双平台",
      "desc_sumup_short": "SSR 47   六星式神 46   签到1106天",
      "equip_type": "0",
      "price": 48000,
      "other_info": {
        "top_heros": [
          {
            "star": 6,
            "name": "赤影妖刀姬",
            "level": 40,
            "max_level": true,
            "rarity": 5,
            "awake": 1,
            "heroId": 328,
            "icon": "https://cbg-yys.res.netease.com//game_res/hero/328/328.png"
          },
          {
            "star": 6,
            "name": "稻荷神御馔津",
            "level": 40,
            "max_level": true,
            "rarity": 5,
            "awake": 1,
            "heroId": 326,
            "icon": "https://cbg-yys.res.netease.com//game_res/hero/326/326.png"
          },
          {
            "star": 6,
            "name": "炼狱茨木童子",
            "level": 40,
            "max_level": true,
            "rarity": 5,
            "awake": 1,
            "heroId": 322,
            "icon": "https://cbg-yys.res.netease.com//game_res/hero/322/322.png"
          },
          {
            "star": 6,
            "name": "烬天玉藻前",
            "level": 40,
            "max_level": true,
            "rarity": 5,
            "awake": 1,
            "heroId": 339,
            "icon": "https://cbg-yys.res.netease.com//game_res/hero/339/339.png"
          },
          {
            "star": 6,
            "name": "御怨般若",
            "level": 40,
            "max_level": true,
            "rarity": 5,
            "awake": 1,
            "heroId": 331,
            "icon": "https://cbg-yys.res.netease.com//game_res/hero/331/331.png"
          }
        ],
        "level_desc": "60级",
        "highlights": [],
        "desc_sumup": "SSR 47   六星式神 46   签到1106天",
        "basic_attrs": [
          "SSR 47",
          "六星式神 46",
          "签到1106天"
        ],
        "icon": "https://cbg-yys.res.netease.com//game_res/hero/328/328.png",
        "desc_sumup_short": "SSR 47   六星式神 46   签到1106天"
      },
      "allow_urs_bargain": false,
      "expire_remain_seconds": 940824,
      "serverid": 10,
      "icon": "https://cbg-yys.res.netease.com//game_res/hero/328/328.png",
      "game_ordersn": "202009111101616-10-ZDEOL4JMQTJLY",
      "platform_type": 2,
      "allow_bargain": false,
      "format_equip_name": "稳名士十套爆伤加",
      "game_channel": "netease"
    },
    {
      "storage_type": 4,
      "tag": "latest",
      "collect_num": 0,
      "pass_fair_show": 0,
      "server_name": "竹之幽",
      "level_desc": "60级",
      "highlights": [],
      "kindid": 1,
      "equip_level": 60,
      "tag_key": "{\"sort_key\": \"recommd\", \"tag\": \"latest\", \"sort_order\": \"\"}",
      "area_name": "中国区-iOS",
      "desc_sumup_short": "SSR 30   六星式神 19   签到968天",
      "equip_type": "0",
      "price": 55000,
      "other_info": {
        "top_heros": [
          {
            "star": 6,
            "name": "烬天玉藻前",
            "level": 40,
            "max_level": true,
            "rarity": 5,
            "awake": 1,
            "heroId": 339,
            "icon": "https://cbg-yys.res.netease.com//game_res/hero/339/339.png"
          },
          {
            "star": 6,
            "name": "炼狱茨木童子",
            "level": 40,
            "max_level": true,
            "rarity": 5,
            "awake": 1,
            "heroId": 322,
            "icon": "https://cbg-yys.res.netease.com//game_res/hero/322/322.png"
          },
          {
            "star": 6,
            "name": "少羽大天狗",
            "level": 40,
            "max_level": true,
            "rarity": 5,
            "awake": 1,
            "heroId": 315,
            "icon": "https://cbg-yys.res.netease.com//game_res/hero/315/315.png"
          },
          {
            "star": 6,
            "name": "辉夜姬",
            "level": 40,
            "max_level": true,
            "rarity": 4,
            "awake": 1,
            "heroId": 280,
            "icon": "https://cbg-yys.res.netease.com//game_res/hero/280/280.png"
          },
          {
            "star": 6,
            "name": "鬼切",
            "level": 40,
            "max_level": true,
            "rarity": 4,
            "awake": 1,
            "heroId": 312,
            "icon": "https://cbg-yys.res.netease.com//game_res/hero/312/312.png"
          }
        ],
        "level_desc": "60级",
        "highlights": [],
        "desc_sumup": "SSR 30   六星式神 19   签到968天",
        "basic_attrs": [
          "SSR 30",
          "六星式神 19",
          "签到968天"
        ],
        "icon": "https://cbg-yys.res.netease.com//game_res/hero/339/339.png",
        "desc_sumup_short": "SSR 30   六星式神 19   签到968天"
      },
      "allow_urs_bargain": false,
      "expire_remain_seconds": 1286420,
      "serverid": 22,
      "icon": "https://cbg-yys.res.netease.com//game_res/hero/339/339.png",
      "game_ordersn": "202009151901616-22-2FQDTYMTNN9XZ",
      "platform_type": 1,
      "allow_bargain": false,
      "format_equip_name": "紅門耖鸡",
      "game_channel": "netease"
    },
    {
      "storage_type": 4,
      "tag": "latest",
      "collect_num": 2,
      "pass_fair_show": 1,
      "server_name": "暖风春穗",
      "level_desc": "60级",
      "highlights": [],
      "kindid": 1,
      "equip_level": 60,
      "tag_key": "{\"sort_key\": \"recommd\", \"tag\": \"latest\", \"sort_order\": \"\"}",
      "area_name": "全平台互通新区",
      "desc_sumup_short": "SSR 43   六星式神 29   签到524天",
      "equip_type": "0",
      "price": 70000,
      "other_info": {
        "top_heros": [
          {
            "star": 6,
            "name": "烬天玉藻前",
            "level": 40,
            "max_level": true,
            "rarity": 5,
            "awake": 1,
            "heroId": 339,
            "icon": "https://cbg-yys.res.netease.com//game_res/hero/339/339.png"
          },
          {
            "star": 6,
            "name": "鬼王酒吞童子",
            "level": 40,
            "max_level": true,
            "rarity": 5,
            "awake": 1,
            "heroId": 341,
            "icon": "https://cbg-yys.res.netease.com//game_res/hero/341/341.png"
          },
          {
            "star": 6,
            "name": "缚骨清姬",
            "level": 40,
            "max_level": true,
            "rarity": 5,
            "awake": 1,
            "heroId": 352,
            "icon": "https://cbg-yys.res.netease.com//game_res/hero/352/352.png"
          },
          {
            "star": 6,
            "name": "炼狱茨木童子",
            "level": 40,
            "max_level": true,
            "rarity": 5,
            "awake": 1,
            "heroId": 322,
            "icon": "https://cbg-yys.res.netease.com//game_res/hero/322/322.png"
          },
          {
            "star": 6,
            "name": "彼岸花",
            "level": 40,
            "max_level": true,
            "rarity": 4,
            "awake": 1,
            "heroId": 288,
            "icon": "https://cbg-yys.res.netease.com//game_res/hero/288/288.png"
          }
        ],
        "level_desc": "60级",
        "highlights": [],
        "desc_sumup": "SSR 43   六星式神 29   签到524天",
        "basic_attrs": [
          "SSR 43",
          "六星式神 29",
          "签到524天"
        ],
        "icon": "https://cbg-yys.res.netease.com//game_res/hero/339/339.png",
        "desc_sumup_short": "SSR 43   六星式神 29   签到524天"
      },
      "allow_urs_bargain": false,
      "expire_remain_seconds": 1199990,
      "serverid": 24,
      "icon": "https://cbg-yys.res.netease.com//game_res/hero/339/339.png",
      "game_ordersn": "202007292201616-24-73DNBYNYMHRXY",
      "platform_type": 1,
      "allow_bargain": false,
      "format_equip_name": "明若秋芬",
      "game_channel": "netease"
    },
    {
      "storage_type": 4,
      "tag": "latest",
      "collect_num": 0,
      "pass_fair_show": 0,
      "server_name": "初心未改",
      "level_desc": "55级",
      "highlights": [],
      "kindid": 1,
      "equip_level": 55,
      "tag_key": "{\"sort_key\": \"recommd\", \"tag\": \"latest\", \"sort_order\": \"\"}",
      "area_name": "全平台互通新区",
      "desc_sumup_short": "SSR 24   六星式神 10   签到229天",
      "equip_type": "0",
      "price": 866600,
      "other_info": {
        "top_heros": [
          {
            "star": 6,
            "name": "炼狱茨木童子",
            "level": 40,
            "max_level": true,
            "rarity": 5,
            "awake": 1,
            "heroId": 322,
            "icon": "https://cbg-yys.res.netease.com//game_res/hero/322/322.png"
          },
          {
            "star": 6,
            "name": "烬天玉藻前",
            "level": 40,
            "max_level": true,
            "rarity": 5,
            "awake": 1,
            "heroId": 339,
            "icon": "https://cbg-yys.res.netease.com//game_res/hero/339/339.png"
          },
          {
            "star": 6,
            "name": "酒吞童子",
            "level": 40,
            "max_level": true,
            "rarity": 4,
            "awake": 1,
            "heroId": 219,
            "icon": "https://cbg-yys.res.netease.com//game_res/hero/219/219.png"
          },
          {
            "star": 6,
            "name": "不知火",
            "level": 40,
            "max_level": true,
            "rarity": 4,
            "awake": 1,
            "heroId": 330,
            "icon": "https://cbg-yys.res.netease.com//game_res/hero/330/330.png"
          },
          {
            "star": 6,
            "name": "云外镜",
            "level": 40,
            "max_level": true,
            "rarity": 4,
            "awake": 1,
            "heroId": 344,
            "icon": "https://cbg-yys.res.netease.com//game_res/hero/344/344.png"
          }
        ],
        "level_desc": "55级",
        "highlights": [],
        "desc_sumup": "SSR 24   六星式神 10   签到229天",
        "basic_attrs": [
          "SSR 24",
          "六星式神 10",
          "签到229天"
        ],
        "icon": "https://cbg-yys.res.netease.com//game_res/hero/322/322.png",
        "desc_sumup_short": "SSR 24   六星式神 10   签到229天"
      },
      "allow_urs_bargain": true,
      "expire_remain_seconds": 1286324,
      "serverid": 28,
      "icon": "https://cbg-yys.res.netease.com//game_res/hero/322/322.png",
      "game_ordersn": "202009151601616-28-AVDOTMXYC3Y0B",
      "platform_type": 1,
      "allow_bargain": true,
      "format_equip_name": "二号位双速18",
      "game_channel": "netease"
    },
    {
      "storage_type": 4,
      "tag": "latest",
      "collect_num": 0,
      "pass_fair_show": 0,
      "server_name": "举手相庆",
      "level_desc": "60级",
      "highlights": [
        "终极之巅",
        "黑晴明"
      ],
      "kindid": 1,
      "equip_level": 60,
      "tag_key": "{\"sort_key\": \"recommd\", \"tag\": \"latest\", \"sort_order\": \"\"}",
      "area_name": "全平台互通新区",
      "desc_sumup_short": "SSR 43   六星式神 72   签到1062天",
      "equip_type": "0",
      "price": 500000,
      "other_info": {
        "top_heros": [
          {
            "star": 6,
            "name": "鬼王酒吞童子",
            "level": 40,
            "max_level": true,
            "rarity": 5,
            "awake": 1,
            "heroId": 341,
            "icon": "https://cbg-yys.res.netease.com//game_res/hero/341/341.png"
          },
          {
            "star": 6,
            "name": "少羽大天狗",
            "level": 40,
            "max_level": true,
            "rarity": 5,
            "awake": 1,
            "heroId": 315,
            "icon": "https://cbg-yys.res.netease.com//game_res/hero/315/315.png"
          },
          {
            "star": 6,
            "name": "天剑韧心鬼切",
            "level": 40,
            "max_level": true,
            "rarity": 5,
            "awake": 1,
            "heroId": 343,
            "icon": "https://cbg-yys.res.netease.com//game_res/hero/343/343.png"
          },
          {
            "star": 6,
            "name": "缚骨清姬",
            "level": 40,
            "max_level": true,
            "rarity": 5,
            "awake": 1,
            "heroId": 352,
            "icon": "https://cbg-yys.res.netease.com//game_res/hero/352/352.png"
          },
          {
            "star": 6,
            "name": "聆海金鱼姬",
            "level": 40,
            "max_level": true,
            "rarity": 5,
            "awake": 1,
            "heroId": 346,
            "icon": "https://cbg-yys.res.netease.com//game_res/hero/346/346.png"
          }
        ],
        "level_desc": "60级",
        "highlights": [
          "终极之巅",
          "黑晴明"
        ],
        "desc_sumup": "SSR 43   六星式神 72   签到1062天",
        "basic_attrs": [
          "SSR 43",
          "六星式神 72",
          "签到1062天"
        ],
        "icon": "https://cbg-yys.res.netease.com//game_res/hero/341/341.png",
        "desc_sumup_short": "SSR 43   六星式神 72   签到1062天"
      },
      "allow_urs_bargain": true,
      "expire_remain_seconds": 1286319,
      "serverid": 23,
      "icon": "https://cbg-yys.res.netease.com//game_res/hero/341/341.png",
      "game_ordersn": "202009151901616-23-B3DSF7AFPDHWY",
      "platform_type": 1,
      "allow_bargain": true,
      "format_equip_name": "上青龙",
      "game_channel": "netease"
    }
  ],
  "pager": {
    "cur_page": 31,
    "total_pages": 100
  }
}